Workbook

Sheet README
A1: Title | B1: Preliminary applicability of MITRE ATT&CK Enterprise v17 techniques to DID/VC systems
A2: Accompanies | B2: T-DID manuscript, Supplementary Material S1 "ATT&CK Applicability Analysis and Threat Correspondence" (Table S4). Public artifact: https://github.com/siksum/T-DID-artifact
A3: Purpose | B3: Before deriving the 21-threat catalog, four of the authors examined every technique of the 14 tactics of ATT&CK Enterprise v17 for its applicability to DID/VC systems. This workbook records the grade and rationale of every analyzed entry. The 21 threats of the catalog were derived from the DID/VC specifications and were not selected from this analysis.
A4: Source framework | B4: MITRE ATT&CK Enterprise v17 (enterprise-attack-17.0, STIX data published by MITRE). Technique and sub-technique names and URLs in this workbook are taken from that release. The final 21-threat correspondence (Supplementary Tables S3 and S4, data/static/attack_elements.csv) uses ATT&CK Enterprise 19.2.
A5: Grades | B5: Full: the attack operates unchanged in a DID/VC environment. Partial: it applies only after the scenario or setting is adapted to DID/VC objects and flows. No: it does not apply. These are the applicability labels of Supplementary Table S4; E, P, A, and None there grade the final threat correspondence instead. Full definitions and grading principles: Criteria sheet.
A6: Unit of analysis | B6: One row of the Entries sheet is one analyzed entry: a sub-technique, or the technique itself when it has no sub-technique (Sub-technique ID empty). A few entries cover several sub-techniques jointly, as in the original analysis.
A7: Technique grade | B7: Techniques sheet: a technique is Full if any of its entries in that tactic is Full; Partial if none is Full and at least one is Partial; No otherwise. A technique listed under several tactics is graded separately in each tactic.
A8: Summary sheet | B8: Per-tactic counts of technique grades computed by formula from the Techniques sheet. Formulas are recalculated when the workbook is opened in a spreadsheet application.
A9: Not graded | B9: T1112 (Modify Registry) is listed under Defense Evasion in v17 but has no entry in the Defense Evasion analysis; it was graded under Persistence. Defense Evasion therefore has 45 techniques, of which 44 were graded.
A10: Translation | B10: The analysis was written in Korean. Rationale, commonalities, differences, and adaptation notes were translated into English without changing their content. Grades are those of the original analysis and were not changed. Some rationales refer to ledger-based DID methods (smart contracts, on-chain/off-chain data), which were within the scope of this preliminary analysis.
A11: Editorial corrections | B11: Technique ID T1506 recorded for Input Capture under Credential Access was corrected to T1056. Misspelled technique and sub-technique names were replaced by the v17 names. Sub-technique names recorded under a different parent technique or under a former name were mapped to their v17 IDs (Corrections sheet). Names that do not correspond to a v17 sub-technique of the listed technique are kept as analyzed and marked in the Note column.
A12: Inspection notes | B12: During translation, rationales of three techniques (seven entries) were found whose wording is in tension with the recorded grade, and three entries carry an unlabeled side annotation in the original sheet; all are listed in the Inspection_notes sheet. The grades are kept as recorded.
... A14: Threat_links sheet | B14: For each of the 21 threats, the ATT&CK technique group of this workbook that Supplementary Table S4 compares with, its applicability grade, the Entries rows, and the final correspondence grade.

Sheet Criteria
A1: Item | B1: Definition | C1: Conditions or rule
A2: Full | B2: The ATT&CK technique has an attack scenario that is structurally identical or directly applicable to a core component of a DID/VC authentication system (DID document, VC, VP, wallet, issuer, verifier, resolver, on-chain registry). | C2: (1) The target directly includes DID/VC-specific assets (private keys, VCs, DID documents, signatures, verification logic). (2) The preconditions of the technique are met by default in a DID/VC operating environment (no additional assumption). (3) A threat scenario structurally equivalent (isomorphic) to the technique is confirmed in the literature or empirically in DID/VC systems.
A3: Partial | B3: The technique applies indirectly to the infrastructure layer (cloud, container, server, network) or to off-chain components of a DID/VC system, and the threat holds only under a specific deployment environment or implementation. | C3: (1) The target is general-purpose infrastructure (OS, cloud, container, network) rather than a DID/VC-specific asset, but an indirect threat arises when that infrastructure runs DID/VC services. (2) A deployment condition such as container-based deployment, a cloud environment, or a specific OS must be assumed for the threat to hold. (3) The outcome can affect the DID/VC authentication flow (issuance, presentation, verification), but the effect is not DID-specific and applies equally to general IT systems.
A4: No | B4: The technique does not form a meaningful threat scenario at any layer of a DID/VC system (core protocol, infrastructure, off-chain), or its preconditions do not hold in a DID/VC operating environment. | C4: (1) The preconditions (specific OS, protocol, hardware) are structurally not met in DID/VC systems. (2) Applying the technique to a DID/VC system has no meaningful effect on the authentication flow, data integrity, or availability. (3) Linking the technique to DID/VC requires three or more assumptions (e.g., Windows desktop + installed DID wallet + registry use), so the realistic threat level is very low.
A5: Principle 1: infrastructure generality | C5: Attacks on general-purpose infrastructure such as containers and operating systems are not threats unique to DID systems, so Partial is the upper bound. Full is assigned only when the technique maps directly to the DID/VC protocol layer.
A6: Principle 2: consistency across tactics | C6: When a technique ID appears in several tactics and the technical basis is the same, the grade must be the same. Contradictory grades are not given on the same basis even when the tactic context (purpose) differs.
A7: Principle 3: three-layer analysis | C7: A DID system is analyzed in three layers: (1) protocol layer (DID document, VC/VP, signature and verification logic, W3C standards), (2) application layer (wallet, agent, issuer and verifier servers), (3) infrastructure layer (cloud, container, OS, network). A protocol-layer threat is Full, an application-layer threat is Partial to Full, and an infrastructure-layer threat is Partial or lower.
A8: Principle 4: conservative grading | C8: If the rationale rates at least one component as high, the minimum condition of that grade is met. If the high rating applies only to the infrastructure layer, the grade cannot exceed Partial.
A9: Source | B9: Overview sheet of the original Korean workbook, section "DID relevance criteria". | C9: Translated into English without changing content. The original workbook does not record whether these criteria were written before or after the tactic analyses; grades in the Entries sheet are those recorded by the analysts.

Sheet Summary
A1: Tactic | B1: Techniques (v17) | C1: Graded | D1: Full | E1: Partial | F1: No
A2: Reconnaissance | B2: =COUNTIF(Techniques!$A$2:$A$246,A2) | C2: =B2-COUNTIFS(Techniques!$A$2:$A$246,A2,Techniques!$H$2:$H$246,"Not graded") | D2: =COUNTIFS(Techniques!$A$2:$A$246,A2,Techniques!$H$2:$H$246,"Full") | E2: =COUNTIFS(Techniques!$A$2:$A$246,A2,Techniques!$H$2:$H$246,"Partial") | F2: =COUNTIFS(Techniques!$A$2:$A$246,A2,Techniques!$H$2:$H$246,"No")
A3: Resource Development | B3: =COUNTIF(Techniques!$A$2:$A$246,A3) | C3: =B3-COUNTIFS(Techniques!$A$2:$A$246,A3,Techniques!$H$2:$H$246,"Not graded") | D3: =COUNTIFS(Techniques!$A$2:$A$246,A3,Techniques!$H$2:$H$246,"Full") | E3: =COUNTIFS(Techniques!$A$2:$A$246,A3,Techniques!$H$2:$H$246,"Partial") | F3: =COUNTIFS(Techniques!$A$2:$A$246,A3,Techniques!$H$2:$H$246,"No")
A4: Initial Access | B4: =COUNTIF(Techniques!$A$2:$A$246,A4) | C4: =B4-COUNTIFS(Techniques!$A$2:$A$246,A4,Techniques!$H$2:$H$246,"Not graded") | D4: =COUNTIFS(Techniques!$A$2:$A$246,A4,Techniques!$H$2:$H$246,"Full") | E4: =COUNTIFS(Techniques!$A$2:$A$246,A4,Techniques!$H$2:$H$246,"Partial") | F4: =COUNTIFS(Techniques!$A$2:$A$246,A4,Techniques!$H$2:$H$246,"No")
A5: Execution | B5: =COUNTIF(Techniques!$A$2:$A$246,A5) | C5: =B5-COUNTIFS(Techniques!$A$2:$A$246,A5,Techniques!$H$2:$H$246,"Not graded") | D5: =COUNTIFS(Techniques!$A$2:$A$246,A5,Techniques!$H$2:$H$246,"Full") | E5: =COUNTIFS(Techniques!$A$2:$A$246,A5,Techniques!$H$2:$H$246,"Partial") | F5: =COUNTIFS(Techniques!$A$2:$A$246,A5,Techniques!$H$2:$H$246,"No")
A6: Persistence | B6: =COUNTIF(Techniques!$A$2:$A$246,A6) | C6: =B6-COUNTIFS(Techniques!$A$2:$A$246,A6,Techniques!$H$2:$H$246,"Not graded") | D6: =COUNTIFS(Techniques!$A$2:$A$246,A6,Techniques!$H$2:$H$246,"Full") | E6: =COUNTIFS(Techniques!$A$2:$A$246,A6,Techniques!$H$2:$H$246,"Partial") | F6: =COUNTIFS(Techniques!$A$2:$A$246,A6,Techniques!$H$2:$H$246,"No")
A7: Privilege Escalation | B7: =COUNTIF(Techniques!$A$2:$A$246,A7) | C7: =B7-COUNTIFS(Techniques!$A$2:$A$246,A7,Techniques!$H$2:$H$246,"Not graded") | D7: =COUNTIFS(Techniques!$A$2:$A$246,A7,Techniques!$H$2:$H$246,"Full") | E7: =COUNTIFS(Techniques!$A$2:$A$246,A7,Techniques!$H$2:$H$246,"Partial") | F7: =COUNTIFS(Techniques!$A$2:$A$246,A7,Techniques!$H$2:$H$246,"No")
A8: Credential Access | B8: =COUNTIF(Techniques!$A$2:$A$246,A8) | C8: =B8-COUNTIFS(Techniques!$A$2:$A$246,A8,Techniques!$H$2:$H$246,"Not graded") | D8: =COUNTIFS(Techniques!$A$2:$A$246,A8,Techniques!$H$2:$H$246,"Full") | E8: =COUNTIFS(Techniques!$A$2:$A$246,A8,Techniques!$H$2:$H$246,"Partial") | F8: =COUNTIFS(Techniques!$A$2:$A$246,A8,Techniques!$H$2:$H$246,"No")
A9: Defense Evasion | B9: =COUNTIF(Techniques!$A$2:$A$246,A9) | C9: =B9-COUNTIFS(Techniques!$A$2:$A$246,A9,Techniques!$H$2:$H$246,"Not graded") | D9: =COUNTIFS(Techniques!$A$2:$A$246,A9,Techniques!$H$2:$H$246,"Full") | E9: =COUNTIFS(Techniques!$A$2:$A$246,A9,Techniques!$H$2:$H$246,"Partial") | F9: =COUNTIFS(Techniques!$A$2:$A$246,A9,Techniques!$H$2:$H$246,"No")
A10: Impact | B10: =COUNTIF(Techniques!$A$2:$A$246,A10) | C10: =B10-COUNTIFS(Techniques!$A$2:$A$246,A10,Techniques!$H$2:$H$246,"Not graded") | D10: =COUNTIFS(Techniques!$A$2:$A$246,A10,Techniques!$H$2:$H$246,"Full") | E10: =COUNTIFS(Techniques!$A$2:$A$246,A10,Techniques!$H$2:$H$246,"Partial") | F10: =COUNTIFS(Techniques!$A$2:$A$246,A10,Techniques!$H$2:$H$246,"No")
A11: Discovery | B11: =COUNTIF(Techniques!$A$2:$A$246,A11) | C11: =B11-COUNTIFS(Techniques!$A$2:$A$246,A11,Techniques!$H$2:$H$246,"Not graded") | D11: =COUNTIFS(Techniques!$A$2:$A$246,A11,Techniques!$H$2:$H$246,"Full") | E11: =COUNTIFS(Techniques!$A$2:$A$246,A11,Techniques!$H$2:$H$246,"Partial") | F11: =COUNTIFS(Techniques!$A$2:$A$246,A11,Techniques!$H$2:$H$246,"No")
A12: Lateral Movement | B12: =COUNTIF(Techniques!$A$2:$A$246,A12) | C12: =B12-COUNTIFS(Techniques!$A$2:$A$246,A12,Techniques!$H$2:$H$246,"Not graded") | D12: =COUNTIFS(Techniques!$A$2:$A$246,A12,Techniques!$H$2:$H$246,"Full") | E12: =COUNTIFS(Techniques!$A$2:$A$246,A12,Techniques!$H$2:$H$246,"Partial") | F12: =COUNTIFS(Techniques!$A$2:$A$246,A12,Techniques!$H$2:$H$246,"No")
A13: Collection | B13: =COUNTIF(Techniques!$A$2:$A$246,A13) | C13: =B13-COUNTIFS(Techniques!$A$2:$A$246,A13,Techniques!$H$2:$H$246,"Not graded") | D13: =COUNTIFS(Techniques!$A$2:$A$246,A13,Techniques!$H$2:$H$246,"Full") | E13: =COUNTIFS(Techniques!$A$2:$A$246,A13,Techniques!$H$2:$H$246,"Partial") | F13: =COUNTIFS(Techniques!$A$2:$A$246,A13,Techniques!$H$2:$H$246,"No")
... A15: Exfiltration | B15: =COUNTIF(Techniques!$A$2:$A$246,A15) | C15: =B15-COUNTIFS(Techniques!$A$2:$A$246,A15,Techniques!$H$2:$H$246,"Not graded") | D15: =COUNTIFS(Techniques!$A$2:$A$246,A15,Techniques!$H$2:$H$246,"Full") | E15: =COUNTIFS(Techniques!$A$2:$A$246,A15,Techniques!$H$2:$H$246,"Partial") | F15: =COUNTIFS(Techniques!$A$2:$A$246,A15,Techniques!$H$2:$H$246,"No")
A16: Total | B16: =SUM(B2:B15) | C16: =SUM(C2:C15) | D16: =SUM(D2:D15) | E16: =SUM(E2:E15) | F16: =SUM(F2:F15)

Sheet Entries
A1: Tactic | B1: Technique ID | C1: Technique | D1: Sub-technique ID | E1: Sub-technique | F1: Grade | G1: Basis for grade | H1: Commonalities | I1: Differences | J1: Adaptation or considerations | K1: Note | L1: ATT&CK URL
A2: Reconnaissance | B2: T1595 | C2: Active Scanning | D2: T1595.001 | E2: Scanning IP Blocks | F2: Partial | G2: Direct probing is not possible, but monitoring is possible using the results of off-chain scanning. | L2: https://attack.mitre.org/techniques/T1595
A3: Reconnaissance | B3: T1595 | C3: Active Scanning | D3: T1595.002 | E3: Vulnerability Scanning | F3: Partial | G3: Direct probing is not possible, but monitoring is possible using the results of off-chain scanning. | L3: https://attack.mitre.org/techniques/T1595
A4: Reconnaissance | B4: T1595 | C4: Active Scanning | D4: T1595.003 | E4: Wordlist Scanning | F4: Partial | G4: Public metadata of smart contracts, such as function names and event names, can be queried. | L4: https://attack.mitre.org/techniques/T1595
A5: Reconnaissance | B5: T1592 | C5: Gather Victim Host Information | D5: T1592.001 | E5: Hardware | F5: No | G5: - | L5: https://attack.mitre.org/techniques/T1592
A6: Reconnaissance | B6: T1592 | C6: Gather Victim Host Information | D6: T1592.002 | E6: Software | F6: Partial | G6: This is not recorded on-chain, but it can be inferred indirectly from smart contract function-call logs and event-emission patterns. | L6: https://attack.mitre.org/techniques/T1592
A7: Reconnaissance | B7: T1592 | C7: Gather Victim Host Information | D7: T1592.003 | E7: Firmware | F7: No | G7: - | L7: https://attack.mitre.org/techniques/T1592
A8: Reconnaissance | B8: T1592 | C8: Gather Victim Host Information | D8: T1592.004 | E8: Client Configurations | F8: Partial | G8: Environment information can be recorded in smart contracts only to a limited extent (indirect information collected off-chain). | L8: https://attack.mitre.org/techniques/T1592
A9: Reconnaissance | B9: T1589 | C9: Gather Victim Identity Information | D9: T1589.001 | E9: Credentials | F9: No | G9: - | L9: https://attack.mitre.org/techniques/T1589
A10: Reconnaissance | B10: T1589 | C10: Gather Victim Identity Information | D10: T1589.002 | E10: Email Addresses | F10: No | G10: - | L10: https://attack.mitre.org/techniques/T1589
A11: Reconnaissance | B11: T1589 | C11: Gather Victim Identity Information | D11: T1589.003 | E11: Employee Names | F11: No | G11: - | L11: https://attack.mitre.org/techniques/T1589
A12: Reconnaissance | B12: T1590 | C12: Gather Victim Network Information | D12: T1590.001 | E12: Domain Properties | F12: No | G12: - | L12: https://attack.mitre.org/techniques/T1590
A13: Reconnaissance | B13: T1590 | C13: Gather Victim Network Information | D13: T1590.002 | E13: DNS | F13: No | G13: - | L13: https://attack.mitre.org/techniques/T1590
... A35: Reconnaissance | B35: T1593 | C35: Search Open Websites/Domains | D35: T1593.003 | E35: Code Repositories | F35: No | G35: - | L35: https://attack.mitre.org/techniques/T1593
A36: Reconnaissance | B36: T1594 | C36: Search Victim-Owned Websites | E36: Search Victim-Owned Websites | F36: No | G36: - | K36: "Search Victim-Owned Websites" is not a v17 sub-technique of T1594; kept as analyzed | L36: https://attack.mitre.org/techniques/T1594
A37: Resource Development | B37: T1650 | C37: Acquire Access | F37: Partial | G37: An attacker can acquire DID/VC accounts, issuer credentials, network access rights, etc. from external sources and attempt authentication while posing as the legitimate owner, or carry out attacks by impersonating an issuer or verifier. Directly tampering with on-chain data is difficult, but privilege theft in off-chain authentication and management systems, accounts, and networks is a real threat. | H37: When externally leaked accounts, privileges, or network access are used in an attack, the same damage occurs: authentication bypass, information leakage, privilege escalation, and system intrusion. | I37: Owing to its on-chain trust structure (immutable records, verification logic, etc.), a DID system is not immediately disabled as a whole even if some privileges are stolen. In conventional systems, the theft of a single privilege can endanger the entire service. | J37: Monitor leakage of sensitive information such as DID/VC service accounts and network access rights; immediately revoke privileges when prior exposure or trading is detected; detect anomalous authentication and access events in real time; and strengthen administrator approval procedures. Reinforce the authentication procedures applied when externally obtained privileges are actually used (multi-factor authentication, device verification, etc.). | L37: https://attack.mitre.org/techniques/T1650
A38: Resource Development | B38: T1583 | C38: Acquire Infrastructure | D38: T1583.001 | E38: Domains | F38: Partial | G38: An attacker can build malicious VC issuance services, fake authentication servers, phishing sites, etc. on self-purchased or leased infrastructure (servers, domains, etc.) and use them to infiltrate the DID/VC authentication ecosystem. On-chain data cannot be tampered with directly, but attack infrastructure such as off-chain issuance/authentication systems and phishing servers is a real threat. | H38: When attack infrastructure (servers, domains, cloud, etc.) is abused, the same damage occurs: phishing, authentication bypass, privilege escalation, and service forgery. | I38: Because a DID system is on-chain based (immutable records, distributed consensus, etc.), some functions (issuance, authentication, etc.) may be constrained when attack infrastructure is set up, but off-chain services can still be targeted. In conventional systems, the scope of damage is larger when a single piece of infrastructure is seized. | J38: When new infrastructure (servers, domains, etc.) appears in the DID/VC ecosystem, strengthen response policies such as blacklisting, automatic anomaly detection, and blocking requests from unregistered infrastructure. Monitor access and authentication events from external infrastructure in real time, and link administrator approval and on-chain records when anomalous behavior occurs. | L38: https://attack.mitre.org/techniques/T1583
A39: Resource Development | B39: T1583 | C39: Acquire Infrastructure | D39: T1583.002 | E39: DNS Server | F39: Partial | G39: An attacker can build malicious VC issuance services, fake authentication servers, phishing sites, etc. on self-purchased or leased infrastructure (servers, domains, etc.) and use them to infiltrate the DID/VC authentication ecosystem. On-chain data cannot be tampered with directly, but attack infrastructure such as off-chain issuance/authentication systems and phishing servers is a real threat. | H39: When attack infrastructure (servers, domains, cloud, etc.) is abused, the same damage occurs: phishing, authentication bypass, privilege escalation, and service forgery. | I39: Because a DID system is on-chain based (immutable records, distributed consensus, etc.), some functions (issuance, authentication, etc.) may be constrained when attack infrastructure is set up, but off-chain services can still be targeted. In conventional systems, the scope of damage is larger when a single piece of infrastructure is seized. | J39: When new infrastructure (servers, domains, etc.) appears in the DID/VC ecosystem, strengthen response policies such as blacklisting, automatic anomaly detection, and blocking requests from unregistered infrastructure. Monitor access and authentication events from external infrastructure in real time, and link administrator approval and on-chain records when anomalous behavior occurs. | L39: https://attack.mitre.org/techniques/T1583
A40: Resource Development | B40: T1583 | C40: Acquire Infrastructure | D40: T1583.003 | E40: Virtual Private Server | F40: Partial | G40: An attacker can build malicious VC issuance services, fake authentication servers, phishing sites, etc. on self-purchased or leased infrastructure (servers, domains, etc.) and use them to infiltrate the DID/VC authentication ecosystem. On-chain data cannot be tampered with directly, but attack infrastructure such as off-chain issuance/authentication systems and phishing servers is a real threat. | H40: When attack infrastructure (servers, domains, cloud, etc.) is abused, the same damage occurs: phishing, authentication bypass, privilege escalation, and service forgery. | I40: Because a DID system is on-chain based (immutable records, distributed consensus, etc.), some functions (issuance, authentication, etc.) may be constrained when attack infrastructure is set up, but off-chain services can still be targeted. In conventional systems, the scope of damage is larger when a single piece of infrastructure is seized. | J40: When new infrastructure (servers, domains, etc.) appears in the DID/VC ecosystem, strengthen response policies such as blacklisting, automatic anomaly detection, and blocking requests from unregistered infrastructure. Monitor access and authentication events from external infrastructure in real time, and link administrator approval and on-chain records when anomalous behavior occurs. | L40: https://attack.mitre.org/techniques/T1583
A41: Resource Development | B41: T1583 | C41: Acquire Infrastructure | D41: T1583.004 | E41: Server | F41: Partial | G41: An attacker can build malicious VC issuance services, fake authentication servers, phishing sites, etc. on self-purchased or leased infrastructure (servers, domains, etc.) and use them to infiltrate the DID/VC authentication ecosystem. On-chain data cannot be tampered with directly, but attack infrastructure such as off-chain issuance/authentication systems and phishing servers is a real threat. | H41: When attack infrastructure (servers, domains, cloud, etc.) is abused, the same damage occurs: phishing, authentication bypass, privilege escalation, and service forgery. | I41: Because a DID system is on-chain based (immutable records, distributed consensus, etc.), some functions (issuance, authentication, etc.) may be constrained when attack infrastructure is set up, but off-chain services can still be targeted. In conventional systems, the scope of damage is larger when a single piece of infrastructure is seized. | J41: When new infrastructure (servers, domains, etc.) appears in the DID/VC ecosystem, strengthen response policies such as blacklisting, automatic anomaly detection, and blocking requests from unregistered infrastructure. Monitor access and authentication events from external infrastructure in real time, and link administrator approval and on-chain records when anomalous behavior occurs. | L41: https://attack.mitre.org/techniques/T1583
A42: Resource Development | B42: T1583 | C42: Acquire Infrastructure | D42: T1583.005 | E42: Botnet | F42: Partial | G42: An attacker can build malicious VC issuance services, fake authentication servers, phishing sites, etc. on self-purchased or leased infrastructure (servers, domains, etc.) and use them to infiltrate the DID/VC authentication ecosystem. On-chain data cannot be tampered with directly, but attack infrastructure such as off-chain issuance/authentication systems and phishing servers is a real threat. | H42: When attack infrastructure (servers, domains, cloud, etc.) is abused, the same damage occurs: phishing, authentication bypass, privilege escalation, and service forgery. | I42: Because a DID system is on-chain based (immutable records, distributed consensus, etc.), some functions (issuance, authentication, etc.) may be constrained when attack infrastructure is set up, but off-chain services can still be targeted. In conventional systems, the scope of damage is larger when a single piece of infrastructure is seized. | J42: When new infrastructure (servers, domains, etc.) appears in the DID/VC ecosystem, strengthen response policies such as blacklisting, automatic anomaly detection, and blocking requests from unregistered infrastructure. Monitor access and authentication events from external infrastructure in real time, and link administrator approval and on-chain records when anomalous behavior occurs. | L42: https://attack.mitre.org/techniques/T1583
A43: Resource Development | B43: T1583 | C43: Acquire Infrastructure | D43: T1583.006 | E43: Web Services | F43: Partial | G43: An attacker can build malicious VC issuance services, fake authentication servers, phishing sites, etc. on self-purchased or leased infrastructure (servers, domains, etc.) and use them to infiltrate the DID/VC authentication ecosystem. On-chain data cannot be tampered with directly, but attack infrastructure such as off-chain issuance/authentication systems and phishing servers is a real threat. | H43: When attack infrastructure (servers, domains, cloud, etc.) is abused, the same damage occurs: phishing, authentication bypass, privilege escalation, and service forgery. | I43: Because a DID system is on-chain based (immutable records, distributed consensus, etc.), some functions (issuance, authentication, etc.) may be constrained when attack infrastructure is set up, but off-chain services can still be targeted. In conventional systems, the scope of damage is larger when a single piece of infrastructure is seized. | J43: When new infrastructure (servers, domains, etc.) appears in the DID/VC ecosystem, strengthen response policies such as blacklisting, automatic anomaly detection, and blocking requests from unregistered infrastructure. Monitor access and authentication events from external infrastructure in real time, and link administrator approval and on-chain records when anomalous behavior occurs. | L43: https://attack.mitre.org/techniques/T1583
A44: Resource Development | B44: T1583 | C44: Acquire Infrastructure | D44: T1583.007 | E44: Serverless | F44: Partial | G44: An attacker can build malicious VC issuance services, fake authentication servers, phishing sites, etc. on self-purchased or leased infrastructure (servers, domains, etc.) and use them to infiltrate the DID/VC authentication ecosystem. On-chain data cannot be tampered with directly, but attack infrastructure such as off-chain issuance/authentication systems and phishing servers is a real threat. | H44: When attack infrastructure (servers, domains, cloud, etc.) is abused, the same damage occurs: phishing, authentication bypass, privilege escalation, and service forgery. | I44: Because a DID system is on-chain based (immutable records, distributed consensus, etc.), some functions (issuance, authentication, etc.) may be constrained when attack infrastructure is set up, but off-chain services can still be targeted. In conventional systems, the scope of damage is larger when a single piece of infrastructure is seized. | J44: When new infrastructure (servers, domains, etc.) appears in the DID/VC ecosystem, strengthen response policies such as blacklisting, automatic anomaly detection, and blocking requests from unregistered infrastructure. Monitor access and authentication events from external infrastructure in real time, and link administrator approval and on-chain records when anomalous behavior occurs. | L44: https://attack.mitre.org/techniques/T1583
A45: Resource Development | B45: T1583 | C45: Acquire Infrastructure | D45: T1583.008 | E45: Malvertising | F45: Partial | G45: An attacker can build malicious VC issuance services, fake authentication servers, phishing sites, etc. on self-purchased or leased infrastructure (servers, domains, etc.) and use them to infiltrate the DID/VC authentication ecosystem. On-chain data cannot be tampered with directly, but attack infrastructure such as off-chain issuance/authentication systems and phishing servers is a real threat. | H45: When attack infrastructure (servers, domains, cloud, etc.) is abused, the same damage occurs: phishing, authentication bypass, privilege escalation, and service forgery. | I45: Because a DID system is on-chain based (immutable records, distributed consensus, etc.), some functions (issuance, authentication, etc.) may be constrained when attack infrastructure is set up, but off-chain services can still be targeted. In conventional systems, the scope of damage is larger when a single piece of infrastructure is seized. | J45: When new infrastructure (servers, domains, etc.) appears in the DID/VC ecosystem, strengthen response policies such as blacklisting, automatic anomaly detection, and blocking requests from unregistered infrastructure. Monitor access and authentication events from external infrastructure in real time, and link administrator approval and on-chain records when anomalous behavior occurs. | L45: https://attack.mitre.org/techniques/T1583
A46: Resource Development | B46: T1586 | C46: Compromise Accounts | D46: T1586.001 | E46: Social Media Accounts | F46: Partial | G46: If accounts of DID/VC issuers, verifiers, or management servers are taken over through phishing, purchase, brute force, etc., various attacks become possible, such as authenticating and issuing as the legitimate owner, privilege escalation, and VC forgery. On-chain data cannot be tampered with directly, but off-chain authentication and management systems become the main targets. | H46: Account takeover can cause the same damage, such as privilege escalation, authentication bypass, and information leakage. | I46: Owing to its on-chain trust structure, a DID system does not immediately lose the trustworthiness of the whole network even if some accounts are taken over. In conventional systems, the takeover of a single key account can expose the entire service to critical risk. | J46: Security policies are needed, such as strong authentication for issuer, verifier, and administrator accounts (multi-factor authentication, OTP), login-history monitoring, detection of abnormal access, immediate blocking and privilege revocation when account takeover is suspected, and stronger on-chain history recording. When account-takeover damage occurs, procedures are needed to assess the scope of impact on the entire service and to revoke privileges and recover promptly. | L46: https://attack.mitre.org/techniques/T1586
A47: Resource Development | B47: T1586 | C47: Compromise Accounts | D47: T1586.002 | E47: Email Accounts | F47: Partial | G47: If accounts of DID/VC issuers, verifiers, or management servers are taken over through phishing, purchase, brute force, etc., various attacks become possible, such as authenticating and issuing as the legitimate owner, privilege escalation, and VC forgery. On-chain data cannot be tampered with directly, but off-chain authentication and management systems become the main targets. | H47: Account takeover can cause the same damage, such as privilege escalation, authentication bypass, and information leakage. | I47: Owing to its on-chain trust structure, a DID system does not immediately lose the trustworthiness of the whole network even if some accounts are taken over. In conventional systems, the takeover of a single key account can expose the entire service to critical risk. | J47: Security policies are needed, such as strong authentication for issuer, verifier, and administrator accounts (multi-factor authentication, OTP), login-history monitoring, detection of abnormal access, immediate blocking and privilege revocation when account takeover is suspected, and stronger on-chain history recording. When account-takeover damage occurs, procedures are needed to assess the scope of impact on the entire service and to revoke privileges and recover promptly. | L47: https://attack.mitre.org/techniques/T1586
A48: Resource Development | B48: T1586 | C48: Compromise Accounts | D48: T1586.003 | E48: Cloud Accounts | F48: Partial | G48: If accounts of DID/VC issuers, verifiers, or management servers are taken over through phishing, purchase, brute force, etc., various attacks become possible, such as authenticating and issuing as the legitimate owner, privilege escalation, and VC forgery. On-chain data cannot be tampered with directly, but off-chain authentication and management systems become the main targets. | H48: Account takeover can cause the same damage, such as privilege escalation, authentication bypass, and information leakage. | I48: Owing to its on-chain trust structure, a DID system does not immediately lose the trustworthiness of the whole network even if some accounts are taken over. In conventional systems, the takeover of a single key account can expose the entire service to critical risk. | J48: Security policies are needed, such as strong authentication for issuer, verifier, and administrator accounts (multi-factor authentication, OTP), login-history monitoring, detection of abnormal access, immediate blocking and privilege revocation when account takeover is suspected, and stronger on-chain history recording. When account-takeover damage occurs, procedures are needed to assess the scope of impact on the entire service and to revoke privileges and recover promptly. | L48: https://attack.mitre.org/techniques/T1586
A49: Resource Development | B49: T1584 | C49: Compromise Infrastructure | D49: T1584.001 | E49: Domains | F49: Partial | G49: Trust-anchoring DID/VC infrastructure (issuers, verifiers, Registry, etc.) can be compromised, enabling attacks disguised as legitimate servers and domains. On-chain data cannot be tampered with directly, but seizing off-chain infrastructure can lead to core threats such as authentication bypass, VC forgery, and information leakage. | H49: Compromise of infrastructure (servers, domains, cloud, etc.) causes the same damage: privilege escalation, authentication bypass, data theft, and collapse of trust. | I49: Owing to its on-chain trust structure and distributed consensus, a DID system does not collapse immediately as a whole even if some infrastructure is compromised. In centralized conventional systems, seizing a single piece of infrastructure can affect the entire service. | J49: Required policies include periodic review of ownership and access rights for DID/VC infrastructure (servers, domains, Registry, etc.), real-time monitoring of anomalous behavior, and prompt privilege revocation and network isolation upon compromise. Infrastructure change, access, and anomaly events should be linked with on-chain records to strengthen trustworthiness, traceability, and auditing. | L49: https://attack.mitre.org/techniques/T1584
... A76: Resource Development | B76: T1608 | C76: Stage Capabilities | D76: T1608.006 | E76: SEO Poisoning | F76: Partial | G76: If an attacker pre-positions (stages) malicious VCs, tampering tools, automation scripts, certificates, etc. on infrastructure inside or outside the DID/VC system, attacks such as authentication bypass, VC forgery, and privilege theft can unfold quickly. Directly tampering with on-chain data is difficult, but staging causes real damage through attacks on off-chain services and systems. | H76: If attack materials such as malware, scripts, and certificates are pre-positioned, they can cause damage such as large-scale infection, authentication bypass, and privilege theft. | I76: Owing to its on-chain trust structure, a DID system may see damage to the overall system dispersed even if materials are staged on some off-chain infrastructure. In centralized conventional systems, the damage is broader when staged materials are executed all at once. | J76: Real-time detection and administrator approval should be strengthened for anomalous behavior, such as placement of new files, scripts, and certificates and upload of unauthorized content, across all infrastructure of the DID/VC service (servers, collaboration tools, cloud, etc.). When attack materials are identified, proactive detection and post-incident response should be strengthened, for example through immediate isolation and linkage with on-chain records. | L76: https://attack.mitre.org/techniques/T1608
A77: Initial Access | B77: T1659 | C77: Content Injection | F77: Partial | G77: Can occur in the web interfaces or API communications of a DID system; content injection attacks are possible during the transmission of VCs (Verifiable Credentials); communication-channel security is important in distributed environments. | H77: The mechanism of injecting malicious content into network communications is the same; the way communication-protocol vulnerabilities are exploited is similar. | I77: In DID, structured data in JSON-LD form can be injected; malicious metadata can be injected through blockchain transactions; content verification mechanisms differ in distributed networks. | J77: Extend network traffic injection to the injection of malicious content into DID Document and VC structures: detect malicious scripts in the serviceEndpoint field of DID Documents; add logic to inspect VC JSON-LD structures for XSS payloads; verify the integrity of DID/VC metadata in on-chain event logs. | L77: https://attack.mitre.org/techniques/T1659
A78: Initial Access | B78: T1189 | C78: Drive-by Compromise | F78: Partial | G78: Applicable when the DID wallet or authentication application is web-based; can occur during browser-based DID authentication; exposure risk when using web-based DID services. | H78: The way browser vulnerabilities are exploited is the same; can execute automatically without user interaction; the infection path via malicious sites is similar. | I78: Aims to steal DID wallet private keys; theft of blockchain connection information and authentication tokens; attempts to gain access rights to the distributed network. | J78: Extend browser-based attacks to DID wallets and VC management applications: add logic for private key theft from web-based DID wallets; detect device-fingerprint changes for VC store theft; detect malicious redirection in QR-code-based DID authentication. | L78: https://attack.mitre.org/techniques/T1189
A79: Initial Access | B79: T1190 | C79: Exploit Public-Facing Application | F79: Full | G79: Vulnerabilities in DID service providers' web applications can be exploited; public DID resolver services can be attacked; public interfaces of blockchain nodes can be attacked. | H79: The exploitation of public-facing application vulnerabilities is the same; targets common infrastructure such as web servers and databases; uses known CVE vulnerabilities. | I79: Attacks specific to DID resolver services; attacks on blockchain RPC endpoints; exploitation of DID authentication service API vulnerabilities. | J79: Extend public-facing application attacks to DID infrastructure services: detect exploitation of DID Universal Resolver API vulnerabilities; add attack patterns against the Credential Status API service; detect attacks on blockchain node RPC interfaces; monitor Schema Fetching service vulnerabilities. | L79: https://attack.mitre.org/techniques/T1190
A80: Initial Access | B80: T1133 | C80: External Remote Services | F80: Partial | G80: Applicable to DID-based SSO (Single Sign-On) systems; access is possible through remote DID authentication services; applies when cloud-based DID services are used. | H80: Uses external access services such as VPN and remote desktop; hard to detect because access is through legitimate authentication; persistent access can be maintained. | I80: Remote access via DID-based authentication; access management in distributed authentication systems; blockchain-based verification of access rights. | J80: Extend external remote services to DID-based authentication systems: detect use of stolen DIDs in DID-based SSO systems; monitor abuse of VC-based remote access rights; analyze multi-service access patterns via DID linkage attacks. | L80: https://attack.mitre.org/techniques/T1133
A81: Initial Access | B81: T1200 | C81: Hardware Additions | F81: Partial | G81: DID systems depend on physical devices such as hardware wallets and mobile devices; private keys and VCs can be stolen through hardware manipulation; the difference is that whereas the goal of the conventional attack is "system control", in DID the goal becomes "identity theft". | H81: Attacks through physical hardware access; security threats can arise when untrusted devices are connected; attacks are carried out without user awareness; interfaces such as USB and NFC are abused. | I81: Conventional: network access, system control, persistence; DID: private key theft, VC misuse, identity authentication bypass. | J81: Change network access to DID key/VC access; change the attack target from enterprise systems to personal wallets/hardware wallets; change system backdoors to DID key cloning/backup. | L81: https://attack.mitre.org/techniques/T1200
A82: Initial Access | B82: T1566 | C82: Phishing | F82: Full | G82: Theft of DID-related credentials is the main goal; private keys or wallet information are collected through phishing; phishing attacks are possible during DID service sign-up. | H82: Email-based social engineering attacks; credential theft through user interaction; infection through malicious links or attachments. | I82: Theft of DID-related credentials (private key, mnemonic phrase); luring users to fake DID service sites; collection of blockchain wallet information. | J82: Extend email phishing to social engineering attacks across the DID ecosystem: add phishing scenarios disguised as VC backup/recovery; detect VC-harvesting attacks via fake Verifier requests; analyze phishing patterns linked with brute-force VC presentation attempts. | L82: https://attack.mitre.org/techniques/T1566
A83: Initial Access | B83: T1566 | C83: Phishing | D83: T1566.001 | E83: Spearphishing Attachment | F83: Full | G83: Theft of DID-related credentials is the main goal; private keys or wallet information are collected through phishing; phishing attacks are possible during DID service sign-up. | H83: Email-based social engineering attacks; credential theft through user interaction; infection through malicious links or attachments. | I83: Theft of DID-related credentials (private key, mnemonic phrase); luring users to fake DID service sites; collection of blockchain wallet information. | J83: Attaching a malicious DID wallet installation file. | L83: https://attack.mitre.org/techniques/T1566
A84: Initial Access | B84: T1566 | C84: Phishing | D84: T1566.002 | E84: Spearphishing Link | F84: Full | G84: Theft of DID-related credentials is the main goal; private keys or wallet information are collected through phishing; phishing attacks are possible during DID service sign-up. | H84: Email-based social engineering attacks; credential theft through user interaction; infection through malicious links or attachments. | I84: Theft of DID-related credentials (private key, mnemonic phrase); luring users to fake DID service sites; collection of blockchain wallet information. | J84: Providing links to fake DID service sites. | L84: https://attack.mitre.org/techniques/T1566
A85: Initial Access | B85: T1566 | C85: Phishing | D85: T1566.003 | E85: Spearphishing via Service | F85: Full | G85: Theft of DID-related credentials is the main goal; private keys or wallet information are collected through phishing; phishing attacks are possible during DID service sign-up. | H85: Email-based social engineering attacks; credential theft through user interaction; infection through malicious links or attachments. | I85: Theft of DID-related credentials (private key, mnemonic phrase); luring users to fake DID service sites; collection of blockchain wallet information. | J85: DID-related phishing via social media or messengers. | L85: https://attack.mitre.org/techniques/T1566
A86: Initial Access | B86: T1566 | C86: Phishing | D86: T1566.004 | E86: Spearphishing Voice | F86: Full | G86: Theft of DID-related credentials is the main goal; private keys or wallet information are collected through phishing; phishing attacks are possible during DID service sign-up. | H86: Email-based social engineering attacks; credential theft through user interaction; infection through malicious links or attachments. | I86: Theft of DID-related credentials (private key, mnemonic phrase); luring users to fake DID service sites; collection of blockchain wallet information. | J86: Collecting DID-related information by telephone. | L86: https://attack.mitre.org/techniques/T1566
A87: Initial Access | B87: T1091 | C87: Replication Through Removable Media | F87: Partial | G87: DID keys and VCs tend to be backed up and moved via removable media; credentials can be replicated via physical media. | H87: Removable storage devices are used as an attack vector; information can be stolen through physical access; autorun functions can be abused; air-gapped systems can be attacked. | I87: Conventional: malware execution, system infection, network propagation; DID: replication of key/VC files, credential misuse, use across multiple devices. | J87: Whereas the conventional technique propagates malware, here DID key/VC files are propagated; autorun malware becomes unauthorized access to backup files; system infection becomes identity replication. | L87: https://attack.mitre.org/techniques/T1091
A88: Initial Access | B88: T1195 | C88: Supply Chain Compromise | F88: Full | G88: Supply chain attacks are possible during DID wallet software development; open-source DID libraries can be manipulated; supply chain attacks during hardware wallet manufacturing. | H88: Manipulation of development tools or libraries; abuse of legitimate software update processes; manipulation during hardware manufacturing. | I88: Manipulation of DID-related cryptographic libraries; supply chain attacks on blockchain client software; supply chain manipulation of hardware wallet firmware. | J88: Extend the software supply chain to the entire DID ecosystem: detect attacks on DID wallet software development toolchains; strengthen integrity verification of open-source DID libraries; monitor supply chain security of hardware wallet firmware; detect manipulation of DID Schema and Context repositories. | L88: https://attack.mitre.org/techniques/T1195
A89: Initial Access | B89: T1195 | C89: Supply Chain Compromise | D89: T1195.001 | E89: Compromise Software Dependencies and Development Tools | F89: Full | G89: Supply chain attacks are possible during DID wallet software development; open-source DID libraries can be manipulated; supply chain attacks during hardware wallet manufacturing. | H89: Manipulation of development tools or libraries; abuse of legitimate software update processes; manipulation during hardware manufacturing. | I89: Manipulation of DID-related cryptographic libraries; supply chain attacks on blockchain client software; supply chain manipulation of hardware wallet firmware. | J89: Manipulation of DID development tools or dependency libraries. | L89: https://attack.mitre.org/techniques/T1195
A90: Initial Access | B90: T1195 | C90: Supply Chain Compromise | D90: T1195.002 | E90: Compromise Software Supply Chain | F90: Full | G90: Supply chain attacks are possible during DID wallet software development; open-source DID libraries can be manipulated; supply chain attacks during hardware wallet manufacturing. | H90: Manipulation of development tools or libraries; abuse of legitimate software update processes; manipulation during hardware manufacturing. | I90: Manipulation of DID-related cryptographic libraries; supply chain attacks on blockchain client software; supply chain manipulation of hardware wallet firmware. | J90: Manipulation of the DID wallet software distribution process. | L90: https://attack.mitre.org/techniques/T1195
A91: Initial Access | B91: T1195 | C91: Supply Chain Compromise | D91: T1195.003 | E91: Compromise Hardware Supply Chain | F91: Full | G91: Supply chain attacks are possible during DID wallet software development; open-source DID libraries can be manipulated; supply chain attacks during hardware wallet manufacturing. | H91: Manipulation of development tools or libraries; abuse of legitimate software update processes; manipulation during hardware manufacturing. | I91: Manipulation of DID-related cryptographic libraries; supply chain attacks on blockchain client software; supply chain manipulation of hardware wallet firmware. | J91: Manipulation of the hardware wallet manufacturing process. | L91: https://attack.mitre.org/techniques/T1195
A92: Initial Access | B92: T1199 | C92: Trusted Relationship | F92: Full | G92: The DID ecosystem is built on trust relationships; trust relationships between Issuers and Verifiers can be abused; trust relationships can be abused in integration with federated identity systems. | H92: Abuse of trust relationships with third-party service providers; attacks on partner accounts with legitimate access rights; lateral attacks through existing trust relationships. | I92: Attacks via theft of DID Issuer privileges; impersonating a trusted Verifier; attacks on trusted nodes within the blockchain network. | J92: Extend trust relationships to the trust chain of the DID ecosystem: detect abuse of Issuer–Verifier trust relationships; monitor attacks on trust bridges between federated identity systems; detect malicious activity within DID delegation chains. | L92: https://attack.mitre.org/techniques/T1199
A93: Initial Access | B93: T1078 | C93: Valid Accounts | D93: T1078.001 | E93: Default Accounts | F93: Full | G93: DID itself is a digital identity and account system; stealing a private key gives complete control over the identity; account management has distinctive characteristics in distributed environments. | H93: Access through legitimate credentials; use of existing access rights and privilege escalation; maintenance of persistent access. | I93: Private-key-based authentication system; risk of unrecoverable account takeover; accounts are hard to trace in distributed environments. | J93: Extend traditional accounts to DID-based identity systems: define attacks that gain complete DID control through private key theft; detect multi-service access patterns after VC wallet theft; monitor privacy violations via DID linkage attacks; attacks on DID accounts with default settings. | L93: https://attack.mitre.org/techniques/T1078
A94: Initial Access | B94: T1078 | C94: Valid Accounts | D94: T1078.002 | E94: Domain Accounts | F94: Full | G94: DID itself is a digital identity and account system; stealing a private key gives complete control over the identity; account management has distinctive characteristics in distributed environments. | H94: Access through legitimate credentials; use of existing access rights and privilege escalation; maintenance of persistent access. | I94: Private-key-based authentication system; risk of unrecoverable account takeover; accounts are hard to trace in distributed environments. | J94: Attacks on organization-level DID accounts. | L94: https://attack.mitre.org/techniques/T1078
A95: Initial Access | B95: T1078 | C95: Valid Accounts | D95: T1078.003 | E95: Local Accounts | F95: Full | G95: DID itself is a digital identity and account system; stealing a private key gives complete control over the identity; account management has distinctive characteristics in distributed environments. | H95: Access through legitimate credentials; use of existing access rights and privilege escalation; maintenance of persistent access. | I95: Private-key-based authentication system; risk of unrecoverable account takeover; accounts are hard to trace in distributed environments. | J95: Attacks on local DID wallet accounts. | L95: https://attack.mitre.org/techniques/T1078
A96: Initial Access | B96: T1078 | C96: Valid Accounts | D96: T1078.004 | E96: Cloud Accounts | F96: Full | G96: DID itself is a digital identity and account system; stealing a private key gives complete control over the identity; account management has distinctive characteristics in distributed environments. | H96: Access through legitimate credentials; use of existing access rights and privilege escalation; maintenance of persistent access. | I96: Private-key-based authentication system; risk of unrecoverable account takeover; accounts are hard to trace in distributed environments. | J96: Attacks on cloud-based DID service accounts. | L96: https://attack.mitre.org/techniques/T1078
A97: Initial Access | B97: T1669 | C97: Wi-Fi Networks | F97: Partial | G97: Mobile DID applications use Wi-Fi networks; performing DID transactions on public Wi-Fi is risky; DID communications can be intercepted at the network level. | H97: Exploitation of wireless network vulnerabilities; interception and manipulation of network traffic; man-in-the-middle (MITM) attacks. | I97: Interception of DID-related blockchain communications; attacks on the private key transmission process; analysis of distributed network communication patterns. | J97: Strengthen encryption of DID communications; additional security measures when using public Wi-Fi; network-level monitoring of DID communications. | L97: https://attack.mitre.org/techniques/T1669
A98: Execution | B98: T1651 | C98: Cloud Administration Command | F98: Partial | G98: If DID authentication systems (DID Agent, VC issuance server, verifier) are operated in a cloud environment, similar attacks can occur indirectly. [Structural relevance] - DID Agent (Cloud VM): High (RunCommand, SSM) - VC Issuer server: Medium (AOBO, JIT privileges) - Revocation API: Medium (manipulable via Runbook) | H98: 1. DID Agents and services can run on AWS or Azure. 2. After stealing privileges, an attacker can execute commands inside the VM. 3. If system administrators or services allow the RunCommand function, command injection is possible. 4. The trust-based structure of the DID network makes lateral movement possible (abuse of trust delegation). | I98: DID system | J98: 1. It is necessary to identify whether the target of RunCommand is a VC issuer or a verifier (fine-grained execution-privilege management per target system). 2. Privilege movement (lateral movement) between trusted DID nodes must be blocked (grant least privilege between nodes). 3. Temporary privileges should be granted on request rather than assigned statically. 4. RunCommand usage should be analyzed together with DID authentication logs (design a structure that cross-analyzes cloud logs and DID event logs). 5. The issuer and system administrator roles must be fully separated (configure authentication and operational privileges independently). | L98: https://attack.mitre.org/techniques/T1651
A99: Execution | B99: T1059 | C99: Command and Scripting Interpreter | D99: T1059.001 | E99: PowerShell | F99: Partial | G99: The DID system itself is not a traditional operating-system or command-line execution environment and therefore does not fully match T1059; however, because it mainly runs as web-based apps (React, Node, etc.), authentication servers (Python, Go), and on cloud-based VMs, it was judged to be partly relevant. [Structural relevance] - DID Wallet (Client): High (JavaScript, React Native, etc.) - DID Agent Server: Medium (Python, Go, Node.js) - CredentialStatus API: High (Node.js, Bash) | H99: 1. Dynamic execution risk: off-chain elements of DID systems (e.g., VC verifiers, wallet apps, CredentialStatus API) are also built with JavaScript, Python, etc., and can dynamically load and execute external data. 2. Possibility of input-driven code execution: in the DID ecosystem as well, user-controllable input can be executed as code within the system when external schemas or presentation requests are processed (eval(), exec()). 3. Attacker-controlled external resources: an attacker can deliver malicious scripts or control execution paths through VC schema URLs, callback URLs, etc. 4. Authentication flow manipulation: command execution can manipulate VC contents, issuance status, presentation flows, etc., creating the possibility of authentication bypass. | I99: DID system | J99: 1. DID environments have no command line, and execution mostly occurs off-chain through API calls or front-end scripts; it would be appropriate to change the framing from command-line-based execution to trust-path-based execution. 2. Reflect authentication flow manipulation in the attack goal: the goal of conventional T1059 is system takeover, whereas in DID the core is VC manipulation, reuse, and bypass. 3. Attacks can occur in various runtimes such as Node.js, React Native, and Python APIs; attack vectors need to be defined for each execution environment. 4. Privacy protection and authentication integrity are important in DID; it would be useful to add threat-assessment factors that reflect the severity of authentication manipulation. | L99: https://attack.mitre.org/techniques/T1059
A100: Execution | B100: T1059 | C100: Command and Scripting Interpreter | D100: T1059.002 | E100: AppleScript | F100: Partial | G100: The DID system itself is not a traditional operating-system or command-line execution environment and therefore does not fully match T1059; however, because it mainly runs as web-based apps (React, Node, etc.), authentication servers (Python, Go), and on cloud-based VMs, it was judged to be partly relevant. [Structural relevance] - DID Wallet (Client): High (JavaScript, React Native, etc.) - DID Agent Server: Medium (Python, Go, Node.js) - CredentialStatus API: High (Node.js, Bash) | H100: 1. Dynamic execution risk: off-chain elements of DID systems (e.g., VC verifiers, wallet apps, CredentialStatus API) are also built with JavaScript, Python, etc., and can dynamically load and execute external data. 2. Possibility of input-driven code execution: in the DID ecosystem as well, user-controllable input can be executed as code within the system when external schemas or presentation requests are processed (eval(), exec()). 3. Attacker-controlled external resources: an attacker can deliver malicious scripts or control execution paths through VC schema URLs, callback URLs, etc. 4. Authentication flow manipulation: command execution can manipulate VC contents, issuance status, presentation flows, etc., creating the possibility of authentication bypass. | I100: DID system | J100: 1. DID environments have no command line, and execution mostly occurs off-chain through API calls or front-end scripts; it would be appropriate to change the framing from command-line-based execution to trust-path-based execution. 2. Reflect authentication flow manipulation in the attack goal: the goal of conventional T1059 is system takeover, whereas in DID the core is VC manipulation, reuse, and bypass. 3. Attacks can occur in various runtimes such as Node.js, React Native, and Python APIs; attack vectors need to be defined for each execution environment. 4. Privacy protection and authentication integrity are important in DID; it would be useful to add threat-assessment factors that reflect the severity of authentication manipulation. | L100: https://attack.mitre.org/techniques/T1059
A101: Execution | B101: T1059 | C101: Command and Scripting Interpreter | D101: T1059.003 | E101: Windows Command Shell | F101: Partial | G101: The DID system itself is not a traditional operating-system or command-line execution environment and therefore does not fully match T1059; however, because it mainly runs as web-based apps (React, Node, etc.), authentication servers (Python, Go), and on cloud-based VMs, it was judged to be partly relevant. [Structural relevance] - DID Wallet (Client): High (JavaScript, React Native, etc.) - DID Agent Server: Medium (Python, Go, Node.js) - CredentialStatus API: High (Node.js, Bash) | H101: 1. Dynamic execution risk: off-chain elements of DID systems (e.g., VC verifiers, wallet apps, CredentialStatus API) are also built with JavaScript, Python, etc., and can dynamically load and execute external data. 2. Possibility of input-driven code execution: in the DID ecosystem as well, user-controllable input can be executed as code within the system when external schemas or presentation requests are processed (eval(), exec()). 3. Attacker-controlled external resources: an attacker can deliver malicious scripts or control execution paths through VC schema URLs, callback URLs, etc. 4. Authentication flow manipulation: command execution can manipulate VC contents, issuance status, presentation flows, etc., creating the possibility of authentication bypass. | I101: Off-chain execution environments such as web apps, mobile apps, and VC verifiers | J101: 1. DID environments have no command line, and execution mostly occurs off-chain through API calls or front-end scripts; it would be appropriate to change the framing from command-line-based execution to trust-path-based execution. 2. Reflect authentication flow manipulation in the attack goal: the goal of conventional T1059 is system takeover, whereas in DID the core is VC manipulation, reuse, and bypass. 3. Attacks can occur in various runtimes such as Node.js, React Native, and Python APIs; attack vectors need to be defined for each execution environment. 4. Privacy protection and authentication integrity are important in DID; it would be useful to add threat-assessment factors that reflect the severity of authentication manipulation. | L101: https://attack.mitre.org/techniques/T1059
A102: Execution | B102: T1059 | C102: Command and Scripting Interpreter | D102: T1059.004 | E102: Unix Shell | F102: Partial | G102: The DID system itself is not a traditional operating-system or command-line execution environment and therefore does not fully match T1059; however, because it mainly runs as web-based apps (React, Node, etc.), authentication servers (Python, Go), and on cloud-based VMs, it was judged to be partly relevant. [Structural relevance] - DID Wallet (Client): High (JavaScript, React Native, etc.) - DID Agent Server: Medium (Python, Go, Node.js) - CredentialStatus API: High (Node.js, Bash) | H102: 1. Dynamic execution risk: off-chain elements of DID systems (e.g., VC verifiers, wallet apps, CredentialStatus API) are also built with JavaScript, Python, etc., and can dynamically load and execute external data. 2. Possibility of input-driven code execution: in the DID ecosystem as well, user-controllable input can be executed as code within the system when external schemas or presentation requests are processed (eval(), exec()). 3. Attacker-controlled external resources: an attacker can deliver malicious scripts or control execution paths through VC schema URLs, callback URLs, etc. 4. Authentication flow manipulation: command execution can manipulate VC contents, issuance status, presentation flows, etc., creating the possibility of authentication bypass. | I102: Off-chain execution environments such as web apps, mobile apps, and VC verifiers | J102: 1. DID environments have no command line, and execution mostly occurs off-chain through API calls or front-end scripts; it would be appropriate to change the framing from command-line-based execution to trust-path-based execution. 2. Reflect authentication flow manipulation in the attack goal: the goal of conventional T1059 is system takeover, whereas in DID the core is VC manipulation, reuse, and bypass. 3. Attacks can occur in various runtimes such as Node.js, React Native, and Python APIs; attack vectors need to be defined for each execution environment. 4. Privacy protection and authentication integrity are important in DID; it would be useful to add threat-assessment factors that reflect the severity of authentication manipulation. | L102: https://attack.mitre.org/techniques/T1059
A103: Execution | B103: T1059 | C103: Command and Scripting Interpreter | D103: T1059.005 | E103: Visual Basic | F103: Partial | G103: The DID system itself is not a traditional operating-system or command-line execution environment and therefore does not fully match T1059; however, because it mainly runs as web-based apps (React, Node, etc.), authentication servers (Python, Go), and on cloud-based VMs, it was judged to be partly relevant. [Structural relevance] - DID Wallet (Client): High (JavaScript, React Native, etc.) - DID Agent Server: Medium (Python, Go, Node.js) - CredentialStatus API: High (Node.js, Bash) | H103: 1. Dynamic execution risk: off-chain elements of DID systems (e.g., VC verifiers, wallet apps, CredentialStatus API) are also built with JavaScript, Python, etc., and can dynamically load and execute external data. 2. Possibility of input-driven code execution: in the DID ecosystem as well, user-controllable input can be executed as code within the system when external schemas or presentation requests are processed (eval(), exec()). 3. Attacker-controlled external resources: an attacker can deliver malicious scripts or control execution paths through VC schema URLs, callback URLs, etc. 4. Authentication flow manipulation: command execution can manipulate VC contents, issuance status, presentation flows, etc., creating the possibility of authentication bypass. | I103: Decentralized clients (DID Wallet), VC verifiers, CredentialStatus API | J103: 1. DID environments have no command line, and execution mostly occurs off-chain through API calls or front-end scripts; it would be appropriate to change the framing from command-line-based execution to trust-path-based execution. 2. Reflect authentication flow manipulation in the attack goal: the goal of conventional T1059 is system takeover, whereas in DID the core is VC manipulation, reuse, and bypass. 3. Attacks can occur in various runtimes such as Node.js, React Native, and Python APIs; attack vectors need to be defined for each execution environment. 4. Privacy protection and authentication integrity are important in DID; it would be useful to add threat-assessment factors that reflect the severity of authentication manipulation. | L103: https://attack.mitre.org/techniques/T1059
A104: Execution | B104: T1059 | C104: Command and Scripting Interpreter | D104: T1059.006 | E104: Python | F104: Partial | G104: The DID system itself is not a traditional operating-system or command-line execution environment and therefore does not fully match T1059; however, because it mainly runs as web-based apps (React, Node, etc.), authentication servers (Python, Go), and on cloud-based VMs, it was judged to be partly relevant. [Structural relevance] - DID Wallet (Client): High (JavaScript, React Native, etc.) - DID Agent Server: Medium (Python, Go, Node.js) - CredentialStatus API: High (Node.js, Bash) | H104: 1. Dynamic execution risk: off-chain elements of DID systems (e.g., VC verifiers, wallet apps, CredentialStatus API) are also built with JavaScript, Python, etc., and can dynamically load and execute external data. 2. Possibility of input-driven code execution: in the DID ecosystem as well, user-controllable input can be executed as code within the system when external schemas or presentation requests are processed (eval(), exec()). 3. Attacker-controlled external resources: an attacker can deliver malicious scripts or control execution paths through VC schema URLs, callback URLs, etc. 4. Authentication flow manipulation: command execution can manipulate VC contents, issuance status, presentation flows, etc., creating the possibility of authentication bypass. | I104: Decentralized clients (DID Wallet), VC verifiers, CredentialStatus API | J104: 1. DID environments have no command line, and execution mostly occurs off-chain through API calls or front-end scripts; it would be appropriate to change the framing from command-line-based execution to trust-path-based execution. 2. Reflect authentication flow manipulation in the attack goal: the goal of conventional T1059 is system takeover, whereas in DID the core is VC manipulation, reuse, and bypass. 3. Attacks can occur in various runtimes such as Node.js, React Native, and Python APIs; attack vectors need to be defined for each execution environment. 4. Privacy protection and authentication integrity are important in DID; it would be useful to add threat-assessment factors that reflect the severity of authentication manipulation. | L104: https://attack.mitre.org/techniques/T1059
A105: Execution | B105: T1059 | C105: Command and Scripting Interpreter | D105: T1059.007 | E105: JavaScript | F105: Partial | G105: The DID system itself is not a traditional operating-system or command-line execution environment and therefore does not fully match T1059; however, because it mainly runs as web-based apps (React, Node, etc.), authentication servers (Python, Go), and on cloud-based VMs, it was judged to be partly relevant. [Structural relevance] - DID Wallet (Client): High (JavaScript, React Native, etc.) - DID Agent Server: Medium (Python, Go, Node.js) - CredentialStatus API: High (Node.js, Bash) | H105: 1. Dynamic execution risk: off-chain elements of DID systems (e.g., VC verifiers, wallet apps, CredentialStatus API) are also built with JavaScript, Python, etc., and can dynamically load and execute external data. 2. Possibility of input-driven code execution: in the DID ecosystem as well, user-controllable input can be executed as code within the system when external schemas or presentation requests are processed (eval(), exec()). 3. Attacker-controlled external resources: an attacker can deliver malicious scripts or control execution paths through VC schema URLs, callback URLs, etc. 4. Authentication flow manipulation: command execution can manipulate VC contents, issuance status, presentation flows, etc., creating the possibility of authentication bypass. | I105: VC forgery, authentication bypass, manipulation of trusted APIs | J105: 1. DID environments have no command line, and execution mostly occurs off-chain through API calls or front-end scripts; it would be appropriate to change the framing from command-line-based execution to trust-path-based execution. 2. Reflect authentication flow manipulation in the attack goal: the goal of conventional T1059 is system takeover, whereas in DID the core is VC manipulation, reuse, and bypass. 3. Attacks can occur in various runtimes such as Node.js, React Native, and Python APIs; attack vectors need to be defined for each execution environment. 4. Privacy protection and authentication integrity are important in DID; it would be useful to add threat-assessment factors that reflect the severity of authentication manipulation. | L105: https://attack.mitre.org/techniques/T1059
A106: Execution | B106: T1059 | C106: Command and Scripting Interpreter | D106: T1059.008 | E106: Network Device CLI | F106: Partial | G106: The DID system itself is not a traditional operating-system or command-line execution environment and therefore does not fully match T1059; however, because it mainly runs as web-based apps (React, Node, etc.), authentication servers (Python, Go), and on cloud-based VMs, it was judged to be partly relevant. [Structural relevance] - DID Wallet (Client): High (JavaScript, React Native, etc.) - DID Agent Server: Medium (Python, Go, Node.js) - CredentialStatus API: High (Node.js, Bash) | H106: 1. Dynamic execution risk: off-chain elements of DID systems (e.g., VC verifiers, wallet apps, CredentialStatus API) are also built with JavaScript, Python, etc., and can dynamically load and execute external data. 2. Possibility of input-driven code execution: in the DID ecosystem as well, user-controllable input can be executed as code within the system when external schemas or presentation requests are processed (eval(), exec()). 3. Attacker-controlled external resources: an attacker can deliver malicious scripts or control execution paths through VC schema URLs, callback URLs, etc. 4. Authentication flow manipulation: command execution can manipulate VC contents, issuance status, presentation flows, etc., creating the possibility of authentication bypass. | I106: VC forgery, authentication bypass, manipulation of trusted APIs | J106: 1. DID environments have no command line, and execution mostly occurs off-chain through API calls or front-end scripts; it would be appropriate to change the framing from command-line-based execution to trust-path-based execution. 2. Reflect authentication flow manipulation in the attack goal: the goal of conventional T1059 is system takeover, whereas in DID the core is VC manipulation, reuse, and bypass. 3. Attacks can occur in various runtimes such as Node.js, React Native, and Python APIs; attack vectors need to be defined for each execution environment. 4. Privacy protection and authentication integrity are important in DID; it would be useful to add threat-assessment factors that reflect the severity of authentication manipulation. | L106: https://attack.mitre.org/techniques/T1059
A107: Execution | B107: T1059 | C107: Command and Scripting Interpreter | D107: T1059.009 | E107: Cloud API | F107: Partial | G107: The DID system itself is not a traditional operating-system or command-line execution environment and therefore does not fully match T1059; however, because it mainly runs as web-based apps (React, Node, etc.), authentication servers (Python, Go), and on cloud-based VMs, it was judged to be partly relevant. [Structural relevance] - DID Wallet (Client): High (JavaScript, React Native, etc.) - DID Agent Server: Medium (Python, Go, Node.js) - CredentialStatus API: High (Node.js, Bash) | H107: 1. Dynamic execution risk: off-chain elements of DID systems (e.g., VC verifiers, wallet apps, CredentialStatus API) are also built with JavaScript, Python, etc., and can dynamically load and execute external data. 2. Possibility of input-driven code execution: in the DID ecosystem as well, user-controllable input can be executed as code within the system when external schemas or presentation requests are processed (eval(), exec()). 3. Attacker-controlled external resources: an attacker can deliver malicious scripts or control execution paths through VC schema URLs, callback URLs, etc. 4. Authentication flow manipulation: command execution can manipulate VC contents, issuance status, presentation flows, etc., creating the possibility of authentication bypass. | I107: Successful authentication with forged VCs, status manipulation, privacy violation | J107: 1. DID environments have no command line, and execution mostly occurs off-chain through API calls or front-end scripts; it would be appropriate to change the framing from command-line-based execution to trust-path-based execution. 2. Reflect authentication flow manipulation in the attack goal: the goal of conventional T1059 is system takeover, whereas in DID the core is VC manipulation, reuse, and bypass. 3. Attacks can occur in various runtimes such as Node.js, React Native, and Python APIs; attack vectors need to be defined for each execution environment. 4. Privacy protection and authentication integrity are important in DID; it would be useful to add threat-assessment factors that reflect the severity of authentication manipulation. | L107: https://attack.mitre.org/techniques/T1059
A108: Execution | B108: T1059 | C108: Command and Scripting Interpreter | D108: T1059.010 | E108: AutoHotKey & AutoIT | F108: Partial | G108: The DID system itself is not a traditional operating-system or command-line execution environment and therefore does not fully match T1059; however, because it mainly runs as web-based apps (React, Node, etc.), authentication servers (Python, Go), and on cloud-based VMs, it was judged to be partly relevant. [Structural relevance] - DID Wallet (Client): High (JavaScript, React Native, etc.) - DID Agent Server: Medium (Python, Go, Node.js) - CredentialStatus API: High (Node.js, Bash) | H108: 1. Dynamic execution risk: off-chain elements of DID systems (e.g., VC verifiers, wallet apps, CredentialStatus API) are also built with JavaScript, Python, etc., and can dynamically load and execute external data. 2. Possibility of input-driven code execution: in the DID ecosystem as well, user-controllable input can be executed as code within the system when external schemas or presentation requests are processed (eval(), exec()). 3. Attacker-controlled external resources: an attacker can deliver malicious scripts or control execution paths through VC schema URLs, callback URLs, etc. 4. Authentication flow manipulation: command execution can manipulate VC contents, issuance status, presentation flows, etc., creating the possibility of authentication bypass. | I108: Successful authentication with forged VCs, status manipulation, privacy violation | J108: 1. DID environments have no command line, and execution mostly occurs off-chain through API calls or front-end scripts; it would be appropriate to change the framing from command-line-based execution to trust-path-based execution. 2. Reflect authentication flow manipulation in the attack goal: the goal of conventional T1059 is system takeover, whereas in DID the core is VC manipulation, reuse, and bypass. 3. Attacks can occur in various runtimes such as Node.js, React Native, and Python APIs; attack vectors need to be defined for each execution environment. 4. Privacy protection and authentication integrity are important in DID; it would be useful to add threat-assessment factors that reflect the severity of authentication manipulation. | L108: https://attack.mitre.org/techniques/T1059
A109: Execution | B109: T1059 | C109: Command and Scripting Interpreter | D109: T1059.011 | E109: Lua | F109: Partial | G109: The DID system itself is not a traditional operating-system or command-line execution environment and therefore does not fully match T1059; however, because it mainly runs as web-based apps (React, Node, etc.), authentication servers (Python, Go), and on cloud-based VMs, it was judged to be partly relevant. [Structural relevance] - DID Wallet (Client): High (JavaScript, React Native, etc.) - DID Agent Server: Medium (Python, Go, Node.js) - CredentialStatus API: High (Node.js, Bash) | H109: 1. Dynamic execution risk: off-chain elements of DID systems (e.g., VC verifiers, wallet apps, CredentialStatus API) are also built with JavaScript, Python, etc., and can dynamically load and execute external data. 2. Possibility of input-driven code execution: in the DID ecosystem as well, user-controllable input can be executed as code within the system when external schemas or presentation requests are processed (eval(), exec()). 3. Attacker-controlled external resources: an attacker can deliver malicious scripts or control execution paths through VC schema URLs, callback URLs, etc. 4. Authentication flow manipulation: command execution can manipulate VC contents, issuance status, presentation flows, etc., creating the possibility of authentication bypass. | I109: Mostly off-chain environments, so traditional detection is not possible; separate behavior-based detection is needed. | J109: 1. DID environments have no command line, and execution mostly occurs off-chain through API calls or front-end scripts; it would be appropriate to change the framing from command-line-based execution to trust-path-based execution. 2. Reflect authentication flow manipulation in the attack goal: the goal of conventional T1059 is system takeover, whereas in DID the core is VC manipulation, reuse, and bypass. 3. Attacks can occur in various runtimes such as Node.js, React Native, and Python APIs; attack vectors need to be defined for each execution environment. 4. Privacy protection and authentication integrity are important in DID; it would be useful to add threat-assessment factors that reflect the severity of authentication manipulation. | L109: https://attack.mitre.org/techniques/T1059
A110: Execution | B110: T1059 | C110: Command and Scripting Interpreter | D110: T1059.012 | E110: Hypervisor CLI | F110: Partial | G110: The DID system itself is not a traditional operating-system or command-line execution environment and therefore does not fully match T1059; however, because it mainly runs as web-based apps (React, Node, etc.), authentication servers (Python, Go), and on cloud-based VMs, it was judged to be partly relevant. [Structural relevance] - DID Wallet (Client): High (JavaScript, React Native, etc.) - DID Agent Server: Medium (Python, Go, Node.js) - CredentialStatus API: High (Node.js, Bash) | H110: 1. Dynamic execution risk: off-chain elements of DID systems (e.g., VC verifiers, wallet apps, CredentialStatus API) are also built with JavaScript, Python, etc., and can dynamically load and execute external data. 2. Possibility of input-driven code execution: in the DID ecosystem as well, user-controllable input can be executed as code within the system when external schemas or presentation requests are processed (eval(), exec()). 3. Attacker-controlled external resources: an attacker can deliver malicious scripts or control execution paths through VC schema URLs, callback URLs, etc. 4. Authentication flow manipulation: command execution can manipulate VC contents, issuance status, presentation flows, etc., creating the possibility of authentication bypass. | I110: Mostly off-chain environments, so traditional detection is not possible; separate behavior-based detection is needed. | J110: 1. DID environments have no command line, and execution mostly occurs off-chain through API calls or front-end scripts; it would be appropriate to change the framing from command-line-based execution to trust-path-based execution. 2. Reflect authentication flow manipulation in the attack goal: the goal of conventional T1059 is system takeover, whereas in DID the core is VC manipulation, reuse, and bypass. 3. Attacks can occur in various runtimes such as Node.js, React Native, and Python APIs; attack vectors need to be defined for each execution environment. 4. Privacy protection and authentication integrity are important in DID; it would be useful to add threat-assessment factors that reflect the severity of authentication manipulation. | L110: https://attack.mitre.org/techniques/T1059
A111: Execution | B111: T1609 | C111: Container Administration Command | F111: Partial | G111: [Judgment: Partial] Execution of container administration commands is an infrastructure-layer (Docker/K8s) threat, i.e., a general infrastructure attack rather than a threat specific to the DID protocol. It requires the premise that the DID system is deployed on containers, so it was judged Partial. DID systems are built as container-based microservices, in which processes such as authentication, VC issuance/verification, and event logging run inside containers. If container administration commands affect the execution environment, they can manipulate or destroy the authentication framework itself. For these reasons it was judged to be highly relevant. [Structural relevance] - VC issuer (container): High (docker exec, entrypoint) - DID Agent server (K8s Pod): High (kubectl exec) - VC status verification API: Medium (access to files inside the container) | H111: 1. DID authentication components often run in Docker/Kubernetes environments. 2. API-based command execution such as kubectl exec and docker exec is possible. 3. VC processing, log files, and status information can be manipulated directly inside containers, giving access to authentication components. 4. Execution privileges are misused when RBAC is inadequate or containers run as root. | I111: DID system | J111: 1. It would be useful to specify security baselines for containers that include authentication components. 2. It would be useful to define RBAC specific to the VC framework. 3. It would be useful to trace behavior semantically to determine whether executed commands affect the authentication flow. 4. Verify integrity based on hashes and SBOMs to detect whether VC-processing container images have changed. | L111: https://attack.mitre.org/techniques/T1609
A112: Execution | B112: T1610 | C112: Deploy Container | F112: Partial | G112: DID authentication frameworks are often container-based, and deploying a new container directly amounts to adding an authentication component. If an attacker deploys an unauthorized container, the VC issuance/verification framework can be abused, which can be a serious threat. [Structural relevance] - VC issuer: High (forgery can be executed by deploying a new issuer container) - DID Agent server: High (deploying a malicious container after stealing Node privileges) - Credential Status API: Medium (posing as a status verification server and returning forged status responses) | H112: 1. DID authentication functions (VC issuance, verification, logging, etc.) are commonly deployed as containers. 2. An attacker can deploy containers resembling the legitimate configuration and disguise them as forged VC issuers/verifiers. 3. The attack risk increases when security settings (Pod Security Policy or Admission Controller) are inadequate. | I112: DID system | J112: 1. Core authentication containers and management containers should be separated, and only internal deployment should be allowed. 2. An image integrity verification scheme should be introduced, making SBOM-based hash verification, and a hash check when deploying VC-processing containers, mandatory. 3. In conjunction with the Admission Controller, VC issuers, status verifiers, etc. should be configured through special policies so that only authorized images/namespaces can be deployed. 4. Containers for authentication components should be designed with a unique label (did.auth=true) to facilitate detection. 5. Authentication logs should be linked with container deployment records so that the origin of authentication actions can be traced. | L112: https://attack.mitre.org/techniques/T1610
A113: Execution | B113: T1675 | C113: ESXi Administration Command | F113: No | G113: Relevant only if the DID authentication system uses virtualized infrastructure (ESXi- or VMware-based clusters). In particular, when microservice-based authentication servers (VP verifier, VC issuer, etc.) are deployed on guest VMs, compromise through ESXi command execution becomes possible. [Structural relevance] - VC issuer guest VM: Low (an ESXi administrator can manipulate the issuance flow) - Credential Status API VM: Low (status responses can be manipulated and logs forged) - DID Agent VM: Low (little impact if it only processes DID-based authentication requests) | H113: - | I113: DID system | J113: - | L113: https://attack.mitre.org/techniques/T1675
A114: Execution | B114: T1203 | C114: Exploitation for Client Execution | F114: Partial | G114: Vulnerabilities in browser-based DID Wallet environments can be exploited, and VC or VP documents delivered in Office or PDF formats can become attack vectors. [Structural relevance] - DID Web-Wallet (browser): High (risk of browser vulnerability exploitation) - DID desktop app (Electron): High (linked to Office/file-format vulnerabilities) - Opening VC/VP attachment documents: High (malicious code in Office or PDF documents can execute) - Server-based components: Low (not a target of traditional exploitation) | H114: 1. Malicious code can be executed on the user's device. 2. Vulnerable apps on the user's device are the main attack targets. 3. Risk of authentication bypass through VC/VP leakage, forgery, or tampering. | I114: DID system | J114: 1. Isolate browser Web Wallets with CSP/iframe and desktop apps with the Electron sandbox. 2. Allow only .vc.json and JWS/JWT formats, and restrict Office/PDF file formats. 3. Automatically verify the digital signature and schema consistency of VCs/VPs before they are opened. 4. Filter VC delivery via email/Office documents at the corporate gateway. 5. Record events such as opening, signature verification, and errors in a unified manner according to the DID protocol specification. | L114: https://attack.mitre.org/techniques/T1203
A115: Execution | B115: T1674 | C115: Input Injection | F115: No | G115: The "automatic execution of browser DevTools" scenario itself is theoretically possible, but in practice attacks based on HID input simulation are unlikely to succeed in browser or mobile app environments. In web environments in particular, secure browser policies (CSP, sandbox) and similar measures apply. Practical Input Injection relies on GUI automation (AutoHotKey, etc.) and is meaningful only for desktop apps. | H115: - | I115: DID system | J115: - | L115: https://attack.mitre.org/techniques/T1674
A116: Execution | B116: T1559 | C116: Inter-Process Communication | D116: T1559.001 | E116: Component Object Model | F116: No | G116: DID systems are not based on an IPC architecture. | H116: - | I116: DID system | J116: - | L116: https://attack.mitre.org/techniques/T1559
A117: Execution | B117: T1559 | C117: Inter-Process Communication | D117: T1559.002 | E117: Dynamic Data Exchange | F117: No | G117: DID systems are not based on an IPC architecture. | H117: - | I117: VC processing flow chaining, log forwarding, status updates, etc. | J117: - | L117: https://attack.mitre.org/techniques/T1559
A118: Execution | B118: T1559 | C118: Inter-Process Communication | D118: T1559.003 | E118: XPC Services | F118: No | G118: DID systems are not based on an IPC architecture. | H118: - | I118: Possibility of authentication manipulation, VC forgery/tampering, and status-report manipulation | J118: - | L118: https://attack.mitre.org/techniques/T1559
A119: Execution | B119: T1106 | C119: Native API | F119: Partial | G119: DID systems have little direct interaction with Native APIs, but if TEEs, wallet applications, or low-level libraries running on servers are present, API calls structurally similar to T1106 can occur. In particular, device-based DID Wallets (mobile) and TEE-based VC issuers can access system resources and perform cryptographic operations through OS Native API calls, so risk factors exist. [Structural relevance] - DID Wallet (app): High (iOS/Android API, WebView, Crypto API) - VC issuer (TEE): High (ARM TrustZone, Intel SGX API) - CredentialStatus API: Medium (possible low-level file access and system API calls) | H119: 1. During DID authentication, structures similar to Native API calls can be used for low-level cryptographic operations, key store access, and environment detection. 2. API calls that access memory regions storing sensitive information such as authentication tokens and keys may exist. 3. Security may be bypassed through TEE regions to which security policies do not apply or through device kernel APIs. | I119: DID system | J119: 1. Because DID authentication systems are client-centric, local calls are hard to trace; monitoring logs of wallet-app API calls need to be obtained. 2. OS-level detection is impossible inside TrustZone/SGX; hash verification of the results of externally delegated execution is needed. 3. Because VC issuance logic can be altered via Native APIs, integrity checks of the legitimate call path and of the VC status verification logic are needed. | L119: https://attack.mitre.org/techniques/T1106
A120: Execution | B120: T1053 | C120: Scheduled Task/Job | D120: T1053.002 | E120: At | F120: Partial | G120: The DID system itself does not directly use traditional OS task schedulers, but its off-chain elements (backend services, certificate issuers, Credential Status API) often run background jobs in containerized environments using scheduling mechanisms such as cron and systemd timers; hence attacks similar to T1053 are possible. [Structural relevance] - VC issuer (Agent Server): High (periodic VC issuance/renewal schedules) - Credential Status API: High (schedule-based status synchronization jobs) - Log server (Audit Logger): Medium (schedule-based compression/backup) - DID Wallet (Client): Low (mostly triggered manually) - Orchestrator (K8s Job, CronJob): Very high (can be leveraged in authentication flows based on automatic execution) | H120: 1. Off-chain microservices run periodically using cron, systemd, etc. 2. Privilege escalation risk: when jobs run with root privileges, an attacker can launch a root shell through a schedule. 3. Backdoor persistence: malicious commands can be executed continuously through periodic schedules. 4. No user involvement: execution is automatic, making detection and awareness difficult. | I120: DID system | J120: 1. Schedule-based authentication flows, such as automatic VC renewal and periodic status checks, need to be managed. 2. Container security policies need to be strengthened, e.g., by minimizing task execution privileges (blocking periodic jobs run as root, applying RBAC, etc.). 3. Task definition hash comparison and integrity checks need to be introduced to detect automated attacks. 4. Schedule changes by an attacker are hard to detect, so integrity checks of the scheduled-task.yaml definition file are needed. | L120: https://attack.mitre.org/techniques/T1053
A121: Execution | B121: T1053 | C121: Scheduled Task/Job | D121: T1053.003 | E121: Cron | F121: Partial | G121: The DID system itself does not directly use traditional OS task schedulers, but its off-chain elements (backend services, certificate issuers, Credential Status API) often run background jobs in containerized environments using scheduling mechanisms such as cron and systemd timers; hence attacks similar to T1053 are possible. [Structural relevance] - VC issuer (Agent Server): High (periodic VC issuance/renewal schedules) - Credential Status API: High (schedule-based status synchronization jobs) - Log server (Audit Logger): Medium (schedule-based compression/backup) - DID Wallet (Client): Low (mostly triggered manually) - Orchestrator (K8s Job, CronJob): Very high (can be leveraged in authentication flows based on automatic execution) | H121: 1. Off-chain microservices run periodically using cron, systemd, etc. 2. Privilege escalation risk: when jobs run with root privileges, an attacker can launch a root shell through a schedule. 3. Backdoor persistence: malicious commands can be executed continuously through periodic schedules. 4. No user involvement: execution is automatic, making detection and awareness difficult. | I121: Container-based Task/Job or Cloud Function | J121: 1. Schedule-based authentication flows, such as automatic VC renewal and periodic status checks, need to be managed. 2. Container security policies need to be strengthened, e.g., by minimizing task execution privileges (blocking periodic jobs run as root, applying RBAC, etc.). 3. Task definition hash comparison and integrity checks need to be introduced to detect automated attacks. 4. Schedule changes by an attacker are hard to detect, so integrity checks of the scheduled-task.yaml definition file are needed. | L121: https://attack.mitre.org/techniques/T1053
A122: Execution | B122: T1053 | C122: Scheduled Task/Job | D122: T1053.005 | E122: Scheduled Task | F122: Partial | G122: The DID system itself does not directly use traditional OS task schedulers, but its off-chain elements (backend services, certificate issuers, Credential Status API) often run background jobs in containerized environments using scheduling mechanisms such as cron and systemd timers; hence attacks similar to T1053 are possible. [Structural relevance] - VC issuer (Agent Server): High (periodic VC issuance/renewal schedules) - Credential Status API: High (schedule-based status synchronization jobs) - Log server (Audit Logger): Medium (schedule-based compression/backup) - DID Wallet (Client): Low (mostly triggered manually) - Orchestrator (K8s Job, CronJob): Very high (can be leveraged in authentication flows based on automatic execution) | H122: 1. Off-chain microservices run periodically using cron, systemd, etc. 2. Privilege escalation risk: when jobs run with root privileges, an attacker can launch a root shell through a schedule. 3. Backdoor persistence: malicious commands can be executed continuously through periodic schedules. 4. No user involvement: execution is automatic, making detection and awareness difficult. | I122: Destruction of authentication trust, automated VC forgery | J122: 1. Schedule-based authentication flows, such as automatic VC renewal and periodic status checks, need to be managed. 2. Container security policies need to be strengthened, e.g., by minimizing task execution privileges (blocking periodic jobs run as root, applying RBAC, etc.). 3. Task definition hash comparison and integrity checks need to be introduced to detect automated attacks. 4. Schedule changes by an attacker are hard to detect, so integrity checks of the scheduled-task.yaml definition file are needed. | L122: https://attack.mitre.org/techniques/T1053
A123: Execution | B123: T1053 | C123: Scheduled Task/Job | D123: T1053.006 | E123: Systemd Timers | F123: Partial | G123: The DID system itself does not directly use traditional OS task schedulers, but its off-chain elements (backend services, certificate issuers, Credential Status API) often run background jobs in containerized environments using scheduling mechanisms such as cron and systemd timers; hence attacks similar to T1053 are possible. [Structural relevance] - VC issuer (Agent Server): High (periodic VC issuance/renewal schedules) - Credential Status API: High (schedule-based status synchronization jobs) - Log server (Audit Logger): Medium (schedule-based compression/backup) - DID Wallet (Client): Low (mostly triggered manually) - Orchestrator (K8s Job, CronJob): Very high (can be leveraged in authentication flows based on automatic execution) | H123: 1. Off-chain microservices run periodically using cron, systemd, etc. 2. Privilege escalation risk: when jobs run with root privileges, an attacker can launch a root shell through a schedule. 3. Backdoor persistence: malicious commands can be executed continuously through periodic schedules. 4. No user involvement: execution is automatic, making detection and awareness difficult. | I123: Inside off-chain authentication modules (Node.js, Python) | J123: 1. Schedule-based authentication flows, such as automatic VC renewal and periodic status checks, need to be managed. 2. Container security policies need to be strengthened, e.g., by minimizing task execution privileges (blocking periodic jobs run as root, applying RBAC, etc.). 3. Task definition hash comparison and integrity checks need to be introduced to detect automated attacks. 4. Schedule changes by an attacker are hard to detect, so integrity checks of the scheduled-task.yaml definition file are needed. | L123: https://attack.mitre.org/techniques/T1053
A124: Execution | B124: T1053 | C124: Scheduled Task/Job | D124: T1053.007 | E124: Container Orchestration Job | F124: Partial | G124: The DID system itself does not directly use traditional OS task schedulers, but its off-chain elements (backend services, certificate issuers, Credential Status API) often run background jobs in containerized environments using scheduling mechanisms such as cron and systemd timers; hence attacks similar to T1053 are possible. [Structural relevance] - VC issuer (Agent Server): High (periodic VC issuance/renewal schedules) - Credential Status API: High (schedule-based status synchronization jobs) - Log server (Audit Logger): Medium (schedule-based compression/backup) - DID Wallet (Client): Low (mostly triggered manually) - Orchestrator (K8s Job, CronJob): Very high (can be leveraged in authentication flows based on automatic execution) | H124: 1. Off-chain microservices run periodically using cron, systemd, etc. 2. Privilege escalation risk: when jobs run with root privileges, an attacker can launch a root shell through a schedule. 3. Backdoor persistence: malicious commands can be executed continuously through periodic schedules. 4. No user involvement: execution is automatic, making detection and awareness difficult. | I124: Cloud-based, so dynamic allocation and randomized execution times are possible | J124: 1. Schedule-based authentication flows, such as automatic VC renewal and periodic status checks, need to be managed. 2. Container security policies need to be strengthened, e.g., by minimizing task execution privileges (blocking periodic jobs run as root, applying RBAC, etc.). 3. Task definition hash comparison and integrity checks need to be introduced to detect automated attacks. 4. Schedule changes by an attacker are hard to detect, so integrity checks of the scheduled-task.yaml definition file are needed. | L124: https://attack.mitre.org/techniques/T1053
A125: Execution | B125: T1648 | C125: Serverless Execution | F125: Partial | G125: The DID system itself is not directly tied to serverless computing, but when VC issuance/verification procedures are implemented as cloud automation flows (Serverless API Gateway + Lambda) or office-based flows (M365 Power Automate), the behavior is similar to this attack technique. [Structural relevance] - Serverless backend of VC issuer: High (AWS Lambda, GCP Cloud Functions, etc.) - DID authentication trigger functions: High (automatic issuance/verification in response to user DID requests) - Power Automate-based VC workflows: Medium (can occur in Office-based integration structures) - Apps Script-based Google Workspace integration: Medium (may include scripts that run automatically when a file is opened) | H125: 1. Serverless functions execute automatically on events and operate without user involvement. 2. Privilege escalation is possible by misusing role-based access control (IAM, etc.). 3. Function logic can be injected or modified externally, and users can hardly notice it. | I125: DID system | J125: 1. Restrict serverless function trigger conditions using a whitelist. 2. Separate the integrity verification logic of VC issuance/verification functions. 3. Minimize IAM policies and block role transitions (PassRole, etc.). 4. For external integration logic such as Power Automate or Apps Script, insert an integrity verification step based on script hash verification. 5. Restrict over-programmed event bindings (e.g., block automatic VC issuance on onCreateUser). | L125: https://attack.mitre.org/techniques/T1648
A126: Execution | B126: T1129 | C126: Shared Modules | F126: No | G126: T1129 is a traditional OS-level execution-based attack and, for the following reasons, has low structural relevance to DID authentication systems: - It presupposes injection of malicious modules operating within native applications or system services on Windows/Linux/macOS, and requires the attacker to have local file system access and the ability to load arbitrary .dll or .so files. - DID authentication systems mostly follow REST API- or JSON-based authentication flows in web/mobile applications, so local native API calls occur only to a limited extent. DID systems are typically built as Node.js, Python, or Go microservices, in which dlopen and LoadLibrary calls are absent or very rare. | H126: - | I126: DID system | J126: - | L126: https://attack.mitre.org/techniques/T1129
A127: Execution | B127: T1072 | C127: Software Deployment Tools | F127: No | G127: Realistically, DID systems are very unlikely to be integrated with SCCM/Intune. Deployment is mostly CI/CD-based (GitHub Actions, GitLab CI, etc.), and they are not EDR targets either. SCCM/Intune are enterprise endpoint-oriented deployment tools whose deployment model differs from that of DID authentication servers (container-based microservices), so relevance is low. | H127: - | I127: DID system | J127: - | L127: https://attack.mitre.org/techniques/T1072
A128: Execution | B128: T1569 | C128: System Services | D128: T1569.001 | E128: Launchctl | F128: No | G128: systemd-based daemon execution occurs only in some on-premises deployments, and most VC issuance/verification components run as containers or serverless functions. "Static systemd service registration" applies only to special on-premises deployment models. | H128: - | I128: DID system | J128: - | L128: https://attack.mitre.org/techniques/T1569
A129: Execution | B129: T1569 | C129: System Services | D129: T1569.002 | E129: Service Execution | F129: No | G129: systemd-based daemon execution occurs only in some on-premises deployments, and most VC issuance/verification components run as containers or serverless functions. "Static systemd service registration" applies only to special on-premises deployment models. | H129: - | I129: Mostly API-based processing; no service registration | J129: - | L129: https://attack.mitre.org/techniques/T1569
A130: Execution | B130: T1569 | C130: System Services | D130: T1569.003 | E130: Systemctl | F130: No | G130: systemd-based daemon execution occurs only in some on-premises deployments, and most VC issuance/verification components run as containers or serverless functions. "Static systemd service registration" applies only to special on-premises deployment models. | H130: - | I130: Deployment privileges are limited, and execution takes place in isolated environments | J130: - | L130: https://attack.mitre.org/techniques/T1569
A131: Execution | B131: T1204 | C131: User Execution | D131: T1204.001 | E131: Malicious Link | F131: Partial | G131: Because DID systems are structured so that client users submit or verify VCs through browsers or mobile apps, the environment allows induced execution via malicious links/scripts. [Structural relevance] - DID Wallet (web/mobile): Medium (users can be lured to malicious VCs or disguised authentication request pages) - VC verifier (web portal): Medium (malicious JavaScript can be induced in the browser) - Cloud server: Low (limited unless an administrator executes it manually) - Container-based issuer: None (not an environment in which external users can induce command execution) | H131: 1. User-action-based execution flows exist: user triggers such as clicking authentication links and VC submission buttons. 2. Possible phishing/spoofing-based threats: users can be lured to forged DID authentication portals. 3. Web-based JavaScript attacks are applicable: CSRF, session hijacking, etc. are possible. | I131: DID system | J131: 1. Block automatic execution of external links and apply a URL whitelist in DID Wallet apps. 2. Strengthen domain validation and signature checks for VC verification request URLs. 3. Display phishing-detection alerts to users at authentication requests (e.g., certificate mismatch warnings). 4. Block iframe and script injection in authentication portals (CSP, XSS protection). | L131: https://attack.mitre.org/techniques/T1204
A132: Execution | B132: T1204 | C132: User Execution | D132: T1204.002 | E132: Malicious File | F132: Partial | G132: Because DID systems are structured so that client users submit or verify VCs through browsers or mobile apps, the environment allows induced execution via malicious links/scripts. [Structural relevance] - DID Wallet (web/mobile): Medium (users can be lured to malicious VCs or disguised authentication request pages) - VC verifier (web portal): Medium (malicious JavaScript can be induced in the browser) - Cloud server: Low (limited unless an administrator executes it manually) - Container-based issuer: None (not an environment in which external users can induce command execution) | H132: 1. User-action-based execution flows exist: user triggers such as clicking authentication links and VC submission buttons. 2. Possible phishing/spoofing-based threats: users can be lured to forged DID authentication portals. 3. Web-based JavaScript attacks are applicable: CSRF, session hijacking, etc. are possible. | I132: Authentication requests via browsers/apps | J132: 1. Block automatic execution of external links and apply a URL whitelist in DID Wallet apps. 2. Strengthen domain validation and signature checks for VC verification request URLs. 3. Display phishing-detection alerts to users at authentication requests (e.g., certificate mismatch warnings). 4. Block iframe and script injection in authentication portals (CSP, XSS protection). | L132: https://attack.mitre.org/techniques/T1204
A133: Execution | B133: T1204 | C133: User Execution | D133: T1204.003 | E133: Malicious Image | F133: Partial | G133: Because DID systems are structured so that client users submit or verify VCs through browsers or mobile apps, the environment allows induced execution via malicious links/scripts. [Structural relevance] - DID Wallet (web/mobile): Medium (users can be lured to malicious VCs or disguised authentication request pages) - VC verifier (web portal): Medium (malicious JavaScript can be induced in the browser) - Cloud server: Low (limited unless an administrator executes it manually) - Container-based issuer: None (not an environment in which external users can induce command execution) | H133: 1. User-action-based execution flows exist: user triggers such as clicking authentication links and VC submission buttons. 2. Possible phishing/spoofing-based threats: users can be lured to forged DID authentication portals. 3. Web-based JavaScript attacks are applicable: CSRF, session hijacking, etc. are possible. | I133: Clicking malicious links, visiting disguised authentication pages, etc. | J133: 1. Block automatic execution of external links and apply a URL whitelist in DID Wallet apps. 2. Strengthen domain validation and signature checks for VC verification request URLs. 3. Display phishing-detection alerts to users at authentication requests (e.g., certificate mismatch warnings). 4. Block iframe and script injection in authentication portals (CSP, XSS protection). | L133: https://attack.mitre.org/techniques/T1204
A134: Execution | B134: T1204 | C134: User Execution | D134: T1204.004 | E134: Malicious Copy and Paste | F134: Partial | G134: Because DID systems are structured so that client users submit or verify VCs through browsers or mobile apps, the environment allows induced execution via malicious links/scripts. [Structural relevance] - DID Wallet (web/mobile): Medium (users can be lured to malicious VCs or disguised authentication request pages) - VC verifier (web portal): Medium (malicious JavaScript can be induced in the browser) - Cloud server: Low (limited unless an administrator executes it manually) - Container-based issuer: None (not an environment in which external users can induce command execution) | H134: 1. User-action-based execution flows exist: user triggers such as clicking authentication links and VC submission buttons. 2. Possible phishing/spoofing-based threats: users can be lured to forged DID authentication portals. 3. Web-based JavaScript attacks are applicable: CSRF, session hijacking, etc. are possible. | I134: UI-based interactions such as QR authentication and VC upload | J134: 1. Block automatic execution of external links and apply a URL whitelist in DID Wallet apps. 2. Strengthen domain validation and signature checks for VC verification request URLs. 3. Display phishing-detection alerts to users at authentication requests (e.g., certificate mismatch warnings). 4. Block iframe and script injection in authentication portals (CSP, XSS protection). | L134: https://attack.mitre.org/techniques/T1204
A135: Execution | B135: T1047 | C135: Windows Management Instrumentation | F135: No | G135: DID authentication systems generally run on Linux/container-based servers, mobile/web apps, blockchain networks, etc., and do not depend on Windows-based service configurations or WMI; WMI is a Windows-only API and has no direct structural relation to DID authentication flows. | H135: - | I135: DID system | J135: - | L135: https://attack.mitre.org/techniques/T1047
A136: Persistence | B136: T1098 | C136: Account Manipulation | D136: T1098.001 | E136: Additional Cloud Credentials | F136: Full | G136: To penetrate the account management system of a target system, the attacker must hold some level of privilege or understand the system's structure. If the attacker steals a private key, all DID authentication becomes possible with that key. Moreover, after stealing a DID key, the attacker can forge VC signatures and manipulate VC contents, enabling (1, 2, 3) changes to privilege levels and (5) extension of the expiry of obtained privileges or insertion of additional privilege information. Alternatively, (4) the attacker can issue fake VCs in bulk to paralyze the DID system and undermine its trustworthiness. | H136: 1. Attacks are carried out by manipulating existing accounts/identities. 2. The attacker seeks to escalate and maintain the privileges of their account. 3. A system's account management logic plays a role similar to private key management logic in DID; by manipulating the private key management logic, the attacker can grant themselves privileges that allow VC forgery. 4. Because legitimate accounts are abused, detection by security systems can be evaded. | I136: - System difference: traditional systems perform authentication based on central servers (LDAP, AD), whereas blockchain-based DID systems perform P2P distributed verification. - Key storage difference: conventionally the server stores password hashes, whereas in blockchain DID each client holds its own private key. - Tracing method: conventionally central server logs can be traced, whereas in DID blockchain transaction records are traced. | J136: 1. Strengthen DID document integrity verification: verify integrity by tracking change history. 2. Key change verification: identify normal key change patterns, monitor the key change process, and detect abnormal key changes. | L136: https://attack.mitre.org/techniques/T1098
A137: Persistence | B137: T1098 | C137: Account Manipulation | D137: T1098.002 | E137: Additional Email Delegate Permissions | F137: Full | G137: To penetrate the account management system of a target system, the attacker must hold some level of privilege or understand the system's structure. If the attacker steals a private key, all DID authentication becomes possible with that key. Moreover, after stealing a DID key, the attacker can forge VC signatures and manipulate VC contents, enabling (1, 2, 3) changes to privilege levels and (5) extension of the expiry of obtained privileges or insertion of additional privilege information. Alternatively, (4) the attacker can issue fake VCs in bulk to paralyze the DID system and undermine its trustworthiness. | H137: 1. Attacks are carried out by manipulating existing accounts/identities. 2. The attacker seeks to escalate and maintain the privileges of their account. 3. A system's account management logic plays a role similar to private key management logic in DID; by manipulating the private key management logic, the attacker can grant themselves privileges that allow VC forgery. 4. Because legitimate accounts are abused, detection by security systems can be evaded. | I137: - System difference: traditional systems perform authentication based on central servers (LDAP, AD), whereas blockchain-based DID systems perform P2P distributed verification. - Key storage difference: conventionally the server stores password hashes, whereas in blockchain DID each client holds its own private key. - Tracing method: conventionally central server logs can be traced, whereas in DID blockchain transaction records are traced. | J137: 1. Strengthen DID document integrity verification: verify integrity by tracking change history. 2. Key change verification: identify normal key change patterns, monitor the key change process, and detect abnormal key changes. | L137: https://attack.mitre.org/techniques/T1098
A138: Persistence | B138: T1098 | C138: Account Manipulation | D138: T1098.003 | E138: Additional Cloud Roles | F138: Full | G138: To penetrate the account management system of a target system, the attacker must hold some level of privilege or understand the system's structure. If the attacker steals a private key, all DID authentication becomes possible with that key. Moreover, after stealing a DID key, the attacker can forge VC signatures and manipulate VC contents, enabling (1, 2, 3) changes to privilege levels and (5) extension of the expiry of obtained privileges or insertion of additional privilege information. Alternatively, (4) the attacker can issue fake VCs in bulk to paralyze the DID system and undermine its trustworthiness. | H138: 1. Attacks are carried out by manipulating existing accounts/identities. 2. The attacker seeks to escalate and maintain the privileges of their account. 3. A system's account management logic plays a role similar to private key management logic in DID; by manipulating the private key management logic, the attacker can grant themselves privileges that allow VC forgery. 4. Because legitimate accounts are abused, detection by security systems can be evaded. | I138: - System difference: traditional systems perform authentication based on central servers (LDAP, AD), whereas blockchain-based DID systems perform P2P distributed verification. - Key storage difference: conventionally the server stores password hashes, whereas in blockchain DID each client holds its own private key. - Tracing method: conventionally central server logs can be traced, whereas in DID blockchain transaction records are traced. | J138: 1. Strengthen DID document integrity verification: verify integrity by tracking change history. 2. Key change verification: identify normal key change patterns, monitor the key change process, and detect abnormal key changes. | L138: https://attack.mitre.org/techniques/T1098
A139: Persistence | B139: T1098 | C139: Account Manipulation | D139: T1098.004 | E139: SSH Authorized Keys | F139: Full | G139: To penetrate the account management system of a target system, the attacker must hold some level of privilege or understand the system's structure. If the attacker steals a private key, all DID authentication becomes possible with that key. Moreover, after stealing a DID key, the attacker can forge VC signatures and manipulate VC contents, enabling (1, 2, 3) changes to privilege levels and (5) extension of the expiry of obtained privileges or insertion of additional privilege information. Alternatively, (4) the attacker can issue fake VCs in bulk to paralyze the DID system and undermine its trustworthiness. | H139: 1. Attacks are carried out by manipulating existing accounts/identities. 2. The attacker seeks to escalate and maintain the privileges of their account. 3. A system's account management logic plays a role similar to private key management logic in DID; by manipulating the private key management logic, the attacker can grant themselves privileges that allow VC forgery. 4. Because legitimate accounts are abused, detection by security systems can be evaded. | I139: - System difference: traditional systems perform authentication based on central servers (LDAP, AD), whereas blockchain-based DID systems perform P2P distributed verification. - Key storage difference: conventionally the server stores password hashes, whereas in blockchain DID each client holds its own private key. - Tracing method: conventionally central server logs can be traced, whereas in DID blockchain transaction records are traced. | J139: 1. Strengthen DID document integrity verification: verify integrity by tracking change history. 2. Key change verification: identify normal key change patterns, monitor the key change process, and detect abnormal key changes. | L139: https://attack.mitre.org/techniques/T1098
A140: Persistence | B140: T1098 | C140: Account Manipulation | D140: T1098.005 | E140: Device Registration | F140: Full | G140: To penetrate the account management system of a target system, the attacker must hold some level of privilege or understand the system's structure. If the attacker steals a private key, all DID authentication becomes possible with that key. Moreover, after stealing a DID key, the attacker can forge VC signatures and manipulate VC contents, enabling (1, 2, 3) changes to privilege levels and (5) extension of the expiry of obtained privileges or insertion of additional privilege information. Alternatively, (4) the attacker can issue fake VCs in bulk to paralyze the DID system and undermine its trustworthiness. | H140: 1. Attacks are carried out by manipulating existing accounts/identities. 2. The attacker seeks to escalate and maintain the privileges of their account. 3. A system's account management logic plays a role similar to private key management logic in DID; by manipulating the private key management logic, the attacker can grant themselves privileges that allow VC forgery. 4. Because legitimate accounts are abused, detection by security systems can be evaded. | I140: - System difference: traditional systems perform authentication based on central servers (LDAP, AD), whereas blockchain-based DID systems perform P2P distributed verification. - Key storage difference: conventionally the server stores password hashes, whereas in blockchain DID each client holds its own private key. - Tracing method: conventionally central server logs can be traced, whereas in DID blockchain transaction records are traced. | J140: 1. Strengthen DID document integrity verification: verify integrity by tracking change history. 2. Key change verification: identify normal key change patterns, monitor the key change process, and detect abnormal key changes. | L140: https://attack.mitre.org/techniques/T1098
A141: Persistence | B141: T1098 | C141: Account Manipulation | D141: T1098.006 | E141: Additional Container Cluster Roles | F141: Full | G141: To penetrate the account management system of a target system, the attacker must hold some level of privilege or understand the system's structure. If the attacker steals a private key, all DID authentication becomes possible with that key. Moreover, after stealing a DID key, the attacker can forge VC signatures and manipulate VC contents, enabling (1, 2, 3) changes to privilege levels and (5) extension of the expiry of obtained privileges or insertion of additional privilege information. Alternatively, (4) the attacker can issue fake VCs in bulk to paralyze the DID system and undermine its trustworthiness. | H141: 1. Attacks are carried out by manipulating existing accounts/identities. 2. The attacker seeks to escalate and maintain the privileges of their account. 3. A system's account management logic plays a role similar to private key management logic in DID; by manipulating the private key management logic, the attacker can grant themselves privileges that allow VC forgery. 4. Because legitimate accounts are abused, detection by security systems can be evaded. | I141: - System difference: traditional systems perform authentication based on central servers (LDAP, AD), whereas blockchain-based DID systems perform P2P distributed verification. - Key storage difference: conventionally the server stores password hashes, whereas in blockchain DID each client holds its own private key. - Tracing method: conventionally central server logs can be traced, whereas in DID blockchain transaction records are traced. | J141: 1. Strengthen DID document integrity verification: verify integrity by tracking change history. 2. Key change verification: identify normal key change patterns, monitor the key change process, and detect abnormal key changes. | L141: https://attack.mitre.org/techniques/T1098
A142: Persistence | B142: T1098 | C142: Account Manipulation | D142: T1098.007 | E142: Additional Local or Domain Groups | F142: Full | G142: To penetrate the account management system of a target system, the attacker must hold some level of privilege or understand the system's structure. If the attacker steals a private key, all DID authentication becomes possible with that key. Moreover, after stealing a DID key, the attacker can forge VC signatures and manipulate VC contents, enabling (1, 2, 3) changes to privilege levels and (5) extension of the expiry of obtained privileges or insertion of additional privilege information. Alternatively, (4) the attacker can issue fake VCs in bulk to paralyze the DID system and undermine its trustworthiness. | H142: 1. Attacks are carried out by manipulating existing accounts/identities. 2. The attacker seeks to escalate and maintain the privileges of their account. 3. A system's account management logic plays a role similar to private key management logic in DID; by manipulating the private key management logic, the attacker can grant themselves privileges that allow VC forgery. 4. Because legitimate accounts are abused, detection by security systems can be evaded. | I142: - System difference: traditional systems perform authentication based on central servers (LDAP, AD), whereas blockchain-based DID systems perform P2P distributed verification. - Key storage difference: conventionally the server stores password hashes, whereas in blockchain DID each client holds its own private key. - Tracing method: conventionally central server logs can be traced, whereas in DID blockchain transaction records are traced. | J142: 1. Strengthen DID document integrity verification: verify integrity by tracking change history. 2. Key change verification: identify normal key change patterns, monitor the key change process, and detect abnormal key changes. | L142: https://attack.mitre.org/techniques/T1098
A143: Persistence | B143: T1197 | C143: BITS Jobs | F143: No | G143: DID systems are web-based services and have no direct relation to Windows BITS. | H143: 1. The attacker performs attack tasks in the background using system resources. 2. Commands are executed and results transmitted through network communication with external servers. 3. Attacks are carried out using system privileges. 4. When a network failure occurs, the running code is automatically re-executed and retried. | I143: - The conventional technique operates via the Windows-only BITS service (COM-based), whereas DID is W3C-based and uses different platforms. - Execution environment difference: the conventional technique runs at the OS system-service level (NT AUTHORITY\SYSTEM), whereas DID runs at the browser/application level. - The conventional technique uses HTTP/HTTPS file transfer (RFC 7230-7235), whereas DID uses a network structure based on JSON-LD data exchange (RFC 8259). - Conventionally, data are processed and used via binary file download/upload, whereas DID processes blockchain-based structured credentials and cryptographic proofs. - Security mechanism difference: Windows ACLs and NTFS permissions conventionally, versus DID public-key cryptography and digital signatures in DID. | J143: - | L143: https://attack.mitre.org/techniques/T1197
A144: Persistence | B144: T1547 | C144: Boot or Logon Autostart Execution | D144: T1547.001 | E144: Registry Run Keys / Startup Folder | F144: Partial | G144: DID services are mainly delivered through the web and applications, so there is almost no direct relation to OS boot; however, threats can arise from the auto-start of apps such as DID wallets. | H144: 1. Performs automatic execution: programs run automatically at system start or user login. 2. Background execution: activity begins in the background without explicit execution by the user. 3. Because it uses legitimate OS auto-start mechanisms, it does not arouse suspicion and can bypass security policies and systems. 4. Even after a system restart, it runs automatically at OS boot and can therefore remain active. | I144: - Conventionally, the attack is performed at the OS kernel/system level, whereas DID mainly operates in browsers/applications. - Conventionally, the attacker can perform the attack only after obtaining administrator privileges, whereas in DID OS administrator privileges are not needed. - To detect the attack, the conventional case requires monitoring the system itself, whereas DID only requires a monitoring system at the browser/application level (somewhat simpler). - The conventional attack runs at the OS level and can threaten the entire system, whereas applied to DID it runs only in a specific browser/application, so its impact is somewhat lower than that of the conventional attack. | J144: 1. When a DID browser/application starts, a filtering security mechanism such as monitoring or whitelisting will be needed. 2. Privilege management of DID wallet browser/app systems needs to be reinforced so that errors in which administrator privileges are executed automatically do not occur. | L144: https://attack.mitre.org/techniques/T1547
A145: Persistence | B145: T1547 | C145: Boot or Logon Autostart Execution | D145: T1547.002 | E145: Authentication Package | F145: Partial | G145: DID services are mainly delivered through the web and applications, so there is almost no direct relation to OS boot; however, threats can arise from the auto-start of apps such as DID wallets. | H145: 1. Performs automatic execution: programs run automatically at system start or user login. 2. Background execution: activity begins in the background without explicit execution by the user. 3. Because it uses legitimate OS auto-start mechanisms, it does not arouse suspicion and can bypass security policies and systems. 4. Even after a system restart, it runs automatically at OS boot and can therefore remain active. | I145: - Conventionally, the attack is performed at the OS kernel/system level, whereas DID mainly operates in browsers/applications. - Conventionally, the attacker can perform the attack only after obtaining administrator privileges, whereas in DID OS administrator privileges are not needed. - To detect the attack, the conventional case requires monitoring the system itself, whereas DID only requires a monitoring system at the browser/application level (somewhat simpler). - The conventional attack runs at the OS level and can threaten the entire system, whereas applied to DID it runs only in a specific browser/application, so its impact is somewhat lower than that of the conventional attack. | J145: 1. When a DID browser/application starts, a filtering security mechanism such as monitoring or whitelisting will be needed. 2. Privilege management of DID wallet browser/app systems needs to be reinforced so that errors in which administrator privileges are executed automatically do not occur. | L145: https://attack.mitre.org/techniques/T1547
A146: Persistence | B146: T1547 | C146: Boot or Logon Autostart Execution | D146: T1547.003 | E146: Time Providers | F146: Partial | G146: DID services are mainly delivered through the web and applications, so there is almost no direct relation to OS boot; however, threats can arise from the auto-start of apps such as DID wallets. | H146: 1. Performs automatic execution: programs run automatically at system start or user login. 2. Background execution: activity begins in the background without explicit execution by the user. 3. Because it uses legitimate OS auto-start mechanisms, it does not arouse suspicion and can bypass security policies and systems. 4. Even after a system restart, it runs automatically at OS boot and can therefore remain active. | I146: - Conventionally, the attack is performed at the OS kernel/system level, whereas DID mainly operates in browsers/applications. - Conventionally, the attacker can perform the attack only after obtaining administrator privileges, whereas in DID OS administrator privileges are not needed. - To detect the attack, the conventional case requires monitoring the system itself, whereas DID only requires a monitoring system at the browser/application level (somewhat simpler). - The conventional attack runs at the OS level and can threaten the entire system, whereas applied to DID it runs only in a specific browser/application, so its impact is somewhat lower than that of the conventional attack. | J146: 1. When a DID browser/application starts, a filtering security mechanism such as monitoring or whitelisting will be needed. 2. Privilege management of DID wallet browser/app systems needs to be reinforced so that errors in which administrator privileges are executed automatically do not occur. | L146: https://attack.mitre.org/techniques/T1547
A147: Persistence | B147: T1547 | C147: Boot or Logon Autostart Execution | D147: T1547.004 | E147: Winlogon Helper DLL | F147: Partial | G147: DID services are mainly delivered through the web and applications, so there is almost no direct relation to OS boot; however, threats can arise from the auto-start of apps such as DID wallets. | H147: 1. Performs automatic execution: programs run automatically at system start or user login. 2. Background execution: activity begins in the background without explicit execution by the user. 3. Because it uses legitimate OS auto-start mechanisms, it does not arouse suspicion and can bypass security policies and systems. 4. Even after a system restart, it runs automatically at OS boot and can therefore remain active. | I147: - Conventionally, the attack is performed at the OS kernel/system level, whereas DID mainly operates in browsers/applications. - Conventionally, the attacker can perform the attack only after obtaining administrator privileges, whereas in DID OS administrator privileges are not needed. - To detect the attack, the conventional case requires monitoring the system itself, whereas DID only requires a monitoring system at the browser/application level (somewhat simpler). - The conventional attack runs at the OS level and can threaten the entire system, whereas applied to DID it runs only in a specific browser/application, so its impact is somewhat lower than that of the conventional attack. | J147: 1. When a DID browser/application starts, a filtering security mechanism such as monitoring or whitelisting will be needed. 2. Privilege management of DID wallet browser/app systems needs to be reinforced so that errors in which administrator privileges are executed automatically do not occur. | L147: https://attack.mitre.org/techniques/T1547
...

Sheet Techniques
A1: Tactic | B1: Technique ID | C1: Technique | D1: Entries | E1: Full entries | F1: Partial entries | G1: No entries | H1: Technique grade
A2: Reconnaissance | B2: T1589 | C2: Gather Victim Identity Information | D2: =COUNTIFS(Entries!$A$2:$A$741,A2,Entries!$B$2:$B$741,B2) | E2: =COUNTIFS(Entries!$A$2:$A$741,A2,Entries!$B$2:$B$741,B2,Entries!$F$2:$F$741,"Full") | F2: =COUNTIFS(Entries!$A$2:$A$741,A2,Entries!$B$2:$B$741,B2,Entries!$F$2:$F$741,"Partial") | G2: =COUNTIFS(Entries!$A$2:$A$741,A2,Entries!$B$2:$B$741,B2,Entries!$F$2:$F$741,"No") | H2: =IF(D2=0,"Not graded",IF(E2>0,"Full",IF(F2>0,"Partial","No")))
A3: Reconnaissance | B3: T1590 | C3: Gather Victim Network Information | D3: =COUNTIFS(Entries!$A$2:$A$741,A3,Entries!$B$2:$B$741,B3) | E3: =COUNTIFS(Entries!$A$2:$A$741,A3,Entries!$B$2:$B$741,B3,Entries!$F$2:$F$741,"Full") | F3: =COUNTIFS(Entries!$A$2:$A$741,A3,Entries!$B$2:$B$741,B3,Entries!$F$2:$F$741,"Partial") | G3: =COUNTIFS(Entries!$A$2:$A$741,A3,Entries!$B$2:$B$741,B3,Entries!$F$2:$F$741,"No") | H3: =IF(D3=0,"Not graded",IF(E3>0,"Full",IF(F3>0,"Partial","No")))
A4: Reconnaissance | B4: T1591 | C4: Gather Victim Org Information | D4: =COUNTIFS(Entries!$A$2:$A$741,A4,Entries!$B$2:$B$741,B4) | E4: =COUNTIFS(Entries!$A$2:$A$741,A4,Entries!$B$2:$B$741,B4,Entries!$F$2:$F$741,"Full") | F4: =COUNTIFS(Entries!$A$2:$A$741,A4,Entries!$B$2:$B$741,B4,Entries!$F$2:$F$741,"Partial") | G4: =COUNTIFS(Entries!$A$2:$A$741,A4,Entries!$B$2:$B$741,B4,Entries!$F$2:$F$741,"No") | H4: =IF(D4=0,"Not graded",IF(E4>0,"Full",IF(F4>0,"Partial","No")))
A5: Reconnaissance | B5: T1592 | C5: Gather Victim Host Information | D5: =COUNTIFS(Entries!$A$2:$A$741,A5,Entries!$B$2:$B$741,B5) | E5: =COUNTIFS(Entries!$A$2:$A$741,A5,Entries!$B$2:$B$741,B5,Entries!$F$2:$F$741,"Full") | F5: =COUNTIFS(Entries!$A$2:$A$741,A5,Entries!$B$2:$B$741,B5,Entries!$F$2:$F$741,"Partial") | G5: =COUNTIFS(Entries!$A$2:$A$741,A5,Entries!$B$2:$B$741,B5,Entries!$F$2:$F$741,"No") | H5: =IF(D5=0,"Not graded",IF(E5>0,"Full",IF(F5>0,"Partial","No")))
A6: Reconnaissance | B6: T1593 | C6: Search Open Websites/Domains | D6: =COUNTIFS(Entries!$A$2:$A$741,A6,Entries!$B$2:$B$741,B6) | E6: =COUNTIFS(Entries!$A$2:$A$741,A6,Entries!$B$2:$B$741,B6,Entries!$F$2:$F$741,"Full") | F6: =COUNTIFS(Entries!$A$2:$A$741,A6,Entries!$B$2:$B$741,B6,Entries!$F$2:$F$741,"Partial") | G6: =COUNTIFS(Entries!$A$2:$A$741,A6,Entries!$B$2:$B$741,B6,Entries!$F$2:$F$741,"No") | H6: =IF(D6=0,"Not graded",IF(E6>0,"Full",IF(F6>0,"Partial","No")))
A7: Reconnaissance | B7: T1594 | C7: Search Victim-Owned Websites | D7: =COUNTIFS(Entries!$A$2:$A$741,A7,Entries!$B$2:$B$741,B7) | E7: =COUNTIFS(Entries!$A$2:$A$741,A7,Entries!$B$2:$B$741,B7,Entries!$F$2:$F$741,"Full") | F7: =COUNTIFS(Entries!$A$2:$A$741,A7,Entries!$B$2:$B$741,B7,Entries!$F$2:$F$741,"Partial") | G7: =COUNTIFS(Entries!$A$2:$A$741,A7,Entries!$B$2:$B$741,B7,Entries!$F$2:$F$741,"No") | H7: =IF(D7=0,"Not graded",IF(E7>0,"Full",IF(F7>0,"Partial","No")))
A8: Reconnaissance | B8: T1595 | C8: Active Scanning | D8: =COUNTIFS(Entries!$A$2:$A$741,A8,Entries!$B$2:$B$741,B8) | E8: =COUNTIFS(Entries!$A$2:$A$741,A8,Entries!$B$2:$B$741,B8,Entries!$F$2:$F$741,"Full") | F8: =COUNTIFS(Entries!$A$2:$A$741,A8,Entries!$B$2:$B$741,B8,Entries!$F$2:$F$741,"Partial") | G8: =COUNTIFS(Entries!$A$2:$A$741,A8,Entries!$B$2:$B$741,B8,Entries!$F$2:$F$741,"No") | H8: =IF(D8=0,"Not graded",IF(E8>0,"Full",IF(F8>0,"Partial","No")))
A9: Reconnaissance | B9: T1596 | C9: Search Open Technical Databases | D9: =COUNTIFS(Entries!$A$2:$A$741,A9,Entries!$B$2:$B$741,B9) | E9: =COUNTIFS(Entries!$A$2:$A$741,A9,Entries!$B$2:$B$741,B9,Entries!$F$2:$F$741,"Full") | F9: =COUNTIFS(Entries!$A$2:$A$741,A9,Entries!$B$2:$B$741,B9,Entries!$F$2:$F$741,"Partial") | G9: =COUNTIFS(Entries!$A$2:$A$741,A9,Entries!$B$2:$B$741,B9,Entries!$F$2:$F$741,"No") | H9: =IF(D9=0,"Not graded",IF(E9>0,"Full",IF(F9>0,"Partial","No")))
A10: Reconnaissance | B10: T1597 | C10: Search Closed Sources | D10: =COUNTIFS(Entries!$A$2:$A$741,A10,Entries!$B$2:$B$741,B10) | E10: =COUNTIFS(Entries!$A$2:$A$741,A10,Entries!$B$2:$B$741,B10,Entries!$F$2:$F$741,"Full") | F10: =COUNTIFS(Entries!$A$2:$A$741,A10,Entries!$B$2:$B$741,B10,Entries!$F$2:$F$741,"Partial") | G10: =COUNTIFS(Entries!$A$2:$A$741,A10,Entries!$B$2:$B$741,B10,Entries!$F$2:$F$741,"No") | H10: =IF(D10=0,"Not graded",IF(E10>0,"Full",IF(F10>0,"Partial","No")))
A11: Reconnaissance | B11: T1598 | C11: Phishing for Information | D11: =COUNTIFS(Entries!$A$2:$A$741,A11,Entries!$B$2:$B$741,B11) | E11: =COUNTIFS(Entries!$A$2:$A$741,A11,Entries!$B$2:$B$741,B11,Entries!$F$2:$F$741,"Full") | F11: =COUNTIFS(Entries!$A$2:$A$741,A11,Entries!$B$2:$B$741,B11,Entries!$F$2:$F$741,"Partial") | G11: =COUNTIFS(Entries!$A$2:$A$741,A11,Entries!$B$2:$B$741,B11,Entries!$F$2:$F$741,"No") | H11: =IF(D11=0,"Not graded",IF(E11>0,"Full",IF(F11>0,"Partial","No")))
A12: Resource Development | B12: T1583 | C12: Acquire Infrastructure | D12: =COUNTIFS(Entries!$A$2:$A$741,A12,Entries!$B$2:$B$741,B12) | E12: =COUNTIFS(Entries!$A$2:$A$741,A12,Entries!$B$2:$B$741,B12,Entries!$F$2:$F$741,"Full") | F12: =COUNTIFS(Entries!$A$2:$A$741,A12,Entries!$B$2:$B$741,B12,Entries!$F$2:$F$741,"Partial") | G12: =COUNTIFS(Entries!$A$2:$A$741,A12,Entries!$B$2:$B$741,B12,Entries!$F$2:$F$741,"No") | H12: =IF(D12=0,"Not graded",IF(E12>0,"Full",IF(F12>0,"Partial","No")))
A13: Resource Development | B13: T1584 | C13: Compromise Infrastructure | D13: =COUNTIFS(Entries!$A$2:$A$741,A13,Entries!$B$2:$B$741,B13) | E13: =COUNTIFS(Entries!$A$2:$A$741,A13,Entries!$B$2:$B$741,B13,Entries!$F$2:$F$741,"Full") | F13: =COUNTIFS(Entries!$A$2:$A$741,A13,Entries!$B$2:$B$741,B13,Entries!$F$2:$F$741,"Partial") | G13: =COUNTIFS(Entries!$A$2:$A$741,A13,Entries!$B$2:$B$741,B13,Entries!$F$2:$F$741,"No") | H13: =IF(D13=0,"Not graded",IF(E13>0,"Full",IF(F13>0,"Partial","No")))
... A246: Exfiltration | B246: T1567 | C246: Exfiltration Over Web Service | D246: =COUNTIFS(Entries!$A$2:$A$741,A246,Entries!$B$2:$B$741,B246) | E246: =COUNTIFS(Entries!$A$2:$A$741,A246,Entries!$B$2:$B$741,B246,Entries!$F$2:$F$741,"Full") | F246: =COUNTIFS(Entries!$A$2:$A$741,A246,Entries!$B$2:$B$741,B246,Entries!$F$2:$F$741,"Partial") | G246: =COUNTIFS(Entries!$A$2:$A$741,A246,Entries!$B$2:$B$741,B246,Entries!$F$2:$F$741,"No") | H246: =IF(D246=0,"Not graded",IF(E246>0,"Full",IF(F246>0,"Partial","No")))

Sheet Threat_links
A1: Threat | B1: Final ATT&CK entry (v19.2) | C1: Final correspondence | D1: Source tactic (v17 analysis) | E1: Source technique | F1: Source applicability | G1: Link | H1: Entries rows | I1: Threat-specific rationale
A2: TDID-THR-001 | B2: T1589 | C2: A | D2: Reconnaissance | E2: T1589 | F2: No | G2: Related source group | H2: 9–11 | I2: Pairwise-DID linking uses a different mechanism
A3: TDID-THR-002 | B3: T1078 | C3: P | D3: Initial Access | E3: T1078 | F3: Full | G3: Related source group | H3: 93–96 | I3: Restricted to key acceptance after a compromise signal
A4: TDID-THR-003 | B4: T1565.001 | C4: E | D4: Impact | E4: T1565 | F4: Full | G4: Related source group | H4: 588–590 | I4: Stored document changed and used after verification
A5: TDID-THR-004 | B5: T1499.003 | C5: E | D5: Impact | E5: T1499 | F5: Partial | G5: Related source group | H5: 596–599 | I5: Equivalent URLs repeatedly invoke a costly function
A6: TDID-THR-005 | B6: – | C6: None | D6: Initial Access | E6: T1190 | F6: Full | G6: Candidate, not adopted | H6: 79 | I6: Not adopted: does not identify parameter injection
A7: TDID-THR-006 | B7: T1565 | C7: E | D7: Impact | E7: T1565 | F7: Full | G7: Related source group | H7: 588–590 | I7: External content manipulation changes processing output
A8: TDID-THR-007 | B8: T1499.004 | C8: P | D8: Impact | E8: T1499 | F8: Partial | G8: Related source group | H8: 596–599 | I8: Requires a cycle in the dereferencing graph
A9: TDID-THR-008 | B9: – | C9: None | D9: Initial Access | E9: T1190 | F9: Full | G9: Candidate, not adopted | H9: 79 | I9: Does not identify duplicate-parameter interpretation differences
A10: TDID-THR-009 | B10: T1499.003 | C10: E | D10: Impact | E10: T1499 | F10: Partial | G10: Related source group | H10: 596–599 | I10: noCache repeatedly invokes a costly function
A11: TDID-THR-010 | B11: – | C11: None | D11: Initial Access | E11: T1190 | F11: Full | G11: Candidate, not adopted | H11: 79 | I11: Does not identify an origin or base-path escape
A12: TDID-THR-011 | B12: T1119 | C12: A | D12: Collection | E12: T1119 | F12: No | G12: Related source group | H12: 678 | I12: Out-of-session tracking differs in collection location and authority
... A22: TDID-THR-021 | B22: T1212 | C22: E | D22: Credential Access | E22: T1212 | F22: Partial | G22: Related source group | H22: 356 | I22: Current-transaction binding failure followed by new-session acceptance

Sheet Corrections
A1: Technique ID (as listed) | B1: Sub-technique (as analyzed) | C1: v17 ID | D1: v17 name | E1: Note
A2: T1506 | B2: (technique ID for Input Capture, Credential Access) | C2: T1056 | D2: Input Capture | E2: ID corrected
A3: T1505 | B3: IIS Web Server | C3: T1505.004 | D3: IIS Components | E3: v17 name: IIS Components
A4: T1505 | B4: Transport Agent (Exchange) | C4: T1505.002 | D4: Transport Agent
A5: T1176 | B5: IDE or Editor Extensions | C5: T1176.002 | D5: IDE Extensions
A6: T1037 | B6: Logon Script (Mac) | C6: T1037.002 | D6: Login Hook | E6: former name of Login Hook
A7: T1543 | B7: Unix Shell Configuration Modification | C7: T1546.004 | D7: Unix Shell Configuration Modification | E7: v17 sub-technique of T1546
A8: T1484 | B8: Domain Trust Modification | C8: T1484.002 | D8: Trust Modification
A9: T1546 | B9: .bash_profile and .bashrc | C9: T1546.004 | D9: Unix Shell Configuration Modification | E9: former name of Unix Shell Configuration Modification
A10: T1546 | B10: Login Item | C10: T1547.015 | D10: Login Items | E10: v17 sub-technique of T1547 (Login Items)
A11: T1574 | B11: DLL Search Order Hijacking | C11: T1574.001 | D11: DLL | E11: merged into T1574.001 (DLL) in v17
A12: T1574 | B12: Shortcut Modification | C12: T1547.009 | D12: Shortcut Modification | E12: v17 sub-technique of T1547
A13: T1574 | B13: Active Setup | C13: T1547.014 | D13: Active Setup | E13: v17 sub-technique of T1547
A14: T1548 | B14: Bypass User Access Control | C14: T1548.002 | D14: Bypass User Account Control
A15: T1564 | B15: Embedded Payloads | C15: T1027.009 | D15: Embedded Payloads | E15: v17 sub-technique of T1027
A16: T1564 | B16: Masquerade Task or Service | C16: T1036.004 | D16: Masquerade Task or Service | E16: v17 sub-technique of T1036
A17: T1564 | B17: Masquerade File Type | C17: T1036.008 | D17: Masquerade File Type | E17: v17 sub-technique of T1036
A18: T1562 | B18: Impair Command History Loggin | C18: T1562.003 | D18: Impair Command History Logging
A19: T1562 | B19: Disalbe or Modify Linux Audit System | C19: T1562.012 | D19: Disable or Modify Linux Audit System
A20: T1556 | B20: Security Support Provider | C20: T1547.005 | D20: Security Support Provider | E20: v17 sub-technique of T1547
A21: T1599 | B21: Network Address Translation (NAT) Traversal | C21: T1599.001 | D21: Network Address Translation Traversal
A22: T1027 | B22: Dynamix API Resolution | C22: T1027.007 | D22: Dynamic API Resolution
A23: T1542 | B23: ROMMON | C23: T1542.004 | D23: ROMMONkit
A24: T1055 | B24: Extrac Window Memory Injection | C24: T1055.011 | D24: Extra Window Memory Injection
A25: T1055 | B25: Process Doppelganging | C25: T1055.013 | D25: Process Doppelgänging
A26: T1218 | B26: InstallUtill | C26: T1218.004 | D26: InstallUtil
A27: T1048 | B27: Exfiltration Over Unencrypted/Obfuscated Non-C2 Protocol | C27: T1048.003 | D27: Exfiltration Over Unencrypted Non-C2 Protocol

Sheet Inspection_notes
A1: Tactic | B1: Technique ID | C1: Sub-technique (as analyzed) | D1: Recorded grade | E1: Observation
A2: Execution | B2: T1675 | C2: - | D2: No | E2: The basis describes conditional applicability with concrete DID/VC impacts (compromise of issuer and status VMs via ESXi commands), the same premise-based reasoning that T1609 uses to justify Partial, yet the grade is No.
A3: Credential Access | B3: T1110 | C3: Credential Stuffing | D3: Partial | E3: The rationale gives only reasons why the technique does not apply (password-based premise versus public-key signatures) and is identical to the rationales of the No-graded Brute Force sub-techniques, which contradicts the Partial grade.
A4: Defense Evasion | B4: T1578 | C4: Create Cloud Instance | D4: Partial | E4: The basis states the technique fully matches T1578 structurally, which corresponds to Full rather than the assigned Partial grade.
A5: Defense Evasion | B5: T1578 | C5: Delete Cloud Instance | D5: Partial | E5: The basis states the technique fully matches T1578 structurally, which corresponds to Full rather than the assigned Partial grade.
A6: Defense Evasion | B6: T1578 | C6: Modify Cloud Instance | D6: Partial | E6: The basis states the technique fully matches T1578 structurally, which corresponds to Full rather than the assigned Partial grade.
A7: Defense Evasion | B7: T1578 | C7: Create Snapshot | D7: Partial | E7: The basis states the technique fully matches T1578 structurally, which corresponds to Full rather than the assigned Partial grade.
A8: Defense Evasion | B8: T1578 | C8: Delete Snapshot | D8: Partial | E8: The basis states the technique fully matches T1578 structurally, which corresponds to Full rather than the assigned Partial grade.
A9: Reconnaissance | B9: T1592 | C9: Hardware | D9: No | E9: The original analysis sheet records No (불일치) in the grade column and an unlabeled side annotation "Partial" (부분일치) beside the row. The recorded grade No is kept.
A10: Reconnaissance | B10: T1590 | C10: Domain Properties | D10: No | E10: The original analysis sheet records No (불일치) in the grade column and an unlabeled side annotation "Partial" (부분일치) beside the row. The recorded grade No is kept.
A11: Reconnaissance | B11: T1591 | C11: Determine Physical Locations | D11: No | E11: The original analysis sheet records No (불일치) in the grade column and an unlabeled side annotation "Partial" (부분일치) beside the row. The recorded grade No is kept.
